src/ALU.v
module alu (
    input [31:0] a,
    input [31:0] b,
    input [3:0] sel,
    output reg [31:0] s,
    output zero
    );

    assign zero = (s == 32'd0);

    always @(*) begin
        case(sel)
            4'd0: s = a + b; //add
            4'd1: s = a - b; //sub
            4'd2: s = a ^ b; //xor
            4'd3: s = a | b; //or
            4'd4: s = a & b; //and
            4'd5: s = a << b[4:0]; //sll
            4'd6: s = a >> b[4:0]; //srl
            4'd7: s = $signed(a) >>> b[4:0]; //sra
            4'd8: s = ($signed(a) < $signed(b)) ? 1 : 0; //slt
            4'd9: s = ($unsigned(a) < $unsigned(b)) ? 1 : 0; //sltu
            4'd10: s = (a == b) ? 1 : 0; //beq
            4'd11: s = (a != b) ? 1 : 0; //bne
            4'd12: s = ($signed(a) >= $signed(b)) ? 1 : 0; //bge
            4'd13: s = ($unsigned(a) >= $unsigned(b)) ? 1 : 0; //bgeu
            4'd14: s = 32'd1; //For unconditional jumpsS 
            default: s = 32'd0;
        endcase
    end
endmodule

tb/tb_ALU.v
`timescale 1ns/1ps


module tb_ALU;

    //input reg
    reg [31:0] a;
    reg [31:0] b;
    reg [3:0] sel;
    //output wire
    wire [31:0] s;
    wire zero;

    alu test_alu (
       .a(a),
       .b(b),
       .sel(sel),
       .s(s),
       .zero(zero) 
    );

    initial begin
        $dumpfile("sim/alu.vcd");
        $dumpvars(0, tb_ALU);

        //add
        a = 32'd1; b = 32'd3; sel = 4'd0;
        #10;  //wait
        if (s !== 32'd4)
            $display("FAIL ADD: expected 4, got %0d", s);
        else
            $display("PASS ADD");

        //overflow edgecase
        a = 32'hFFFFFFFF; b = 32'd1; sel = 4'd0;
        #10;
        if (s !== 32'd0)
            $display("FAIL ADD overflow: expected 0, got %0d", s);
        else
            $display("PASS ADD overflow");

        //adding zeros
        a = 32'd0; b = 32'd0; sel = 4'd0;
        #10;
        if (s !== 32'd0)
            $display("FAIL ADD zero: expected 0, got %0d", s);
        else
            $display("PASS ADD zero");

        //sub
        a = 32'd11; b = 32'd6; sel = 4'd1;
        #10;
        if (s !== 32'd5)
            $display("FAIL SUB: expected 5, got %0d", s);
        else
            $display("PASS SUB");

        //sub overflow
        a = 32'd3; b = 32'd6; sel = 4'd1;
        #10;
        if (s !== 32'hFFFFFFFD)
            $display("FAIL SUB overflow: expected -3, got %0d", s);
        else
            $display("PASS SUB overflow");

        //subtract to 0
        a = 32'd6; b = 32'd6; sel = 4'd1;
        #10;
        if (s !== 32'd0)
            $display("FAIL SUB zero: expected 0, got %0d", s);
        else
            $display("PASS SUB zero");

        //xor
        a = 32'h00000FFF; b = 32'h000000BD; sel = 4'd2;
        #10;
        if (s !== 32'h00000F42)
            $display("FAIL XOR: expected 00000F42, got %0d", s);
        else
            $display("PASS XOR");

        //or
        a = 32'h0000FEFE; b = 32'hF000AABB; sel = 4'd3;
        #10;
        if (s !== 32'hF000FEFF)
            $display("FAIL OR: expected F000FEFF, got %0d", s);
        else
            $display("PASS OR");

        //and
        a = 32'h0000FEFE; b = 32'hF000AABB; sel = 4'd4;
        #10;
        if (s !== 32'h0000AABA)
            $display("FAIL AND: expected 0000AABA, got %0d", s);
        else
            $display("PASS AND");

        //sll
        a = 32'd1; b = 32'd3; sel = 4'd5;
        #10;
        if (s !== 32'd8)
            $display("FAIL SLL: expected 8, got %0d", s);
        else
            $display("PASS SLL");

        //sll overflow
        a = 32'd2; b = 32'd31; sel = 4'd5;
        #10;
        if (s !== 32'd0)
            $display("FAIL SLL: expected 0, got %0d", s);
        else
            $display("PASS SLL");
        
        //srl
        a = 32'd4; b = 32'd2; sel = 4'd6;
        #10;
        if (s !== 32'd1)
            $display("FAIL SRL: expected 1, got %0d", s);
        else
            $display("PASS SRL");

        //srl neg & overflow
        a = 32'hF0000000; b = 32'd31; sel = 4'd6;
        #10;
        if (s !== 32'd1)
            $display("FAIL SRL edge: expected 1, got %0d", s);
        else
            $display("PASS SRL edge");

        //sra
        a = 32'hF0000000; b = 32'd31; sel = 4'd7;
        #10;
        if (s !== 32'hFFFFFFFF)
            $display("FAIL SRA neg: expected -1, got %0d", s);
        else
            $display("PASS SRA neg");

        a = 32'h70000000; b = 32'd31; sel = 4'd7;
        #10;
        if (s !== 32'd0)
            $display("FAIL SRA pos: expected 0, got %0d", s);
        else
            $display("PASS SRA pos");

        //slt
        a = 32'd8; b = 32'd10; sel = 4'd8;
        #10;
        if (s !== 32'd1)
            $display("FAIL SLT: expected 1, got %0d", s);
        else
            $display("PASS SLT");

        a = 32'd8; b = 32'd8; sel = 4'd8;
        #10;
        if (s !== 32'd0)
            $display("FAIL SLT equal: expected 0, got %0d", s);
        else
            $display("PASS SLT equal");

        a = 32'd8; b = 32'hF0000000; sel = 4'd8;
        #10;
        if (s !== 32'd0)
            $display("FAIL SLT neg: expected 0, got %0d", s);
        else
            $display("PASS SLT neg");

        //sltu
        a = 32'd8; b = 32'd10; sel = 4'd9;
        #10;
        if (s !== 32'd1)
            $display("FAIL SLTU: expected 1, got %0d", s);
        else
            $display("PASS SLTU");

        a = 32'd8; b = 32'd8; sel = 4'd9;
        #10;
        if (s !== 32'd0)
            $display("FAIL SLTU equal: expected 0, got %0d", s);
        else
            $display("PASS SLTU equal");

        a = 32'd8; b = 32'hF0000000; sel = 4'd9;
        #10;
        if (s !== 32'd1)
            $display("FAIL SLTU neg: expected 1, got %0d", s);
        else
            $display("PASS SLTU neg");

        //eq
        a = 32'd12; b = 32'd12; sel = 4'd10;
        #10;
        if (s !== 32'd1)
            $display("FAIL EQ1: expected 1, got %0d", s);
        else
            $display("PASS EQ1");

        a = 32'd8; b = 32'hF0000000; sel = 4'd10;
        #10;
        if (s !== 32'd0)
            $display("FAIL EQ0: expected 0, got %0d", s);
        else
            $display("PASS EQ0");

        //neq
        a = 32'd8; b = 32'd99; sel = 4'd11;
        #10;
        if (s !== 32'd1)
            $display("FAIL NEQ1: expected 1, got %0d", s);
        else
            $display("PASS NEQ1");

        a = 32'd42; b = 32'd42; sel = 4'd11;
        #10;
        if (s !== 32'd0)
            $display("FAIL NEQ0: expected 0, got %0d", s);
        else
            $display("PASS NEQ0");

        //bge
        a = 32'd8; b = 32'd10; sel = 4'd12;
        #10;
        if (s !== 32'd0)
            $display("FAIL BGE: expected 0, got %0d", s);
        else
            $display("PASS BGE");

        a = 32'd8; b = 32'd8; sel = 4'd12;
        #10;
        if (s !== 32'd1)
            $display("FAIL BGE equal: expected 1, got %0d", s);
        else
            $display("PASS BGE equal");

        a = 32'd8; b = 32'hF0000000; sel = 4'd12;
        #10;
        if (s !== 32'd1)
            $display("FAIL BGE neg: expected 1, got %0d", s);
        else
            $display("PASS BGE neg");

        //bge
        a = 32'd8; b = 32'd10; sel = 4'd13;
        #10;
        if (s !== 32'd0)
            $display("FAIL BGEU: expected 0, got %0d", s);
        else
            $display("PASS BGEU");

        a = 32'd8; b = 32'd8; sel = 4'd13;
        #10;
        if (s !== 32'd1)
            $display("FAIL BGEU equal: expected 1, got %0d", s);
        else
            $display("PASS BGEU equal");

        a = 32'd8; b = 32'hF0000000; sel = 4'd13;
        #10;
        if (s !== 32'd0)
            $display("FAIL BGEU neg: expected 0, got %0d", s);
        else
            $display("PASS BGEU neg");
        
        $finish;

    end

endmodule;

sim/alu.vcd
$date
	Sat Jun  6 21:38:00 2026
$end
$version
	Icarus Verilog
$end
$timescale
	1ps
$end
$scope module tb_ALU $end
$var wire 1 ! zero $end
$var wire 32 " s [31:0] $end
$var reg 32 # a [31:0] $end
$var reg 32 $ b [31:0] $end
$var reg 4 % sel [3:0] $end
$scope module test_alu $end
$var wire 32 & a [31:0] $end
$var wire 32 ' b [31:0] $end
$var wire 4 ( sel [3:0] $end
$var wire 1 ! zero $end
$var reg 32 ) s [31:0] $end
$upscope $end
$upscope $end
$enddefinitions $end
$comment Show the parameter values. $end
$dumpall
$end
#0
$dumpvars
b100 )
b0 (
b11 '
b1 &
b0 %
b11 $
b1 #
b100 "
0!
$end
#10000
1!
b0 "
b0 )
b1 $
b1 '
b11111111111111111111111111111111 #
b11111111111111111111111111111111 &
#20000
b0 $
b0 '
b0 #
b0 &
#30000
0!
b101 "
b101 )
b1 %
b1 (
b110 $
b110 '
b1011 #
b1011 &
#40000
b11111111111111111111111111111101 "
b11111111111111111111111111111101 )
b11 #
b11 &
#50000
1!
b0 "
b0 )
b110 #
b110 &
#60000
0!
b111101000010 "
b111101000010 )
b10 %
b10 (
b10111101 $
b10111101 '
b111111111111 #
b111111111111 &
#70000
b11110000000000001111111011111111 "
b11110000000000001111111011111111 )
b11 %
b11 (
b11110000000000001010101010111011 $
b11110000000000001010101010111011 '
b1111111011111110 #
b1111111011111110 &
#80000
b1010101010111010 "
b1010101010111010 )
b100 %
b100 (
#90000
b1000 "
b1000 )
b101 %
b101 (
b11 $
b11 '
b1 #
b1 &
#100000
1!
b0 "
b0 )
b11111 $
b11111 '
b10 #
b10 &
#110000
0!
b1 "
b1 )
b110 %
b110 (
b10 $
b10 '
b100 #
b100 &
#120000
b11111 $
b11111 '
b11110000000000000000000000000000 #
b11110000000000000000000000000000 &
#130000
b11111111111111111111111111111111 "
b11111111111111111111111111111111 )
b111 %
b111 (
#140000
1!
b0 "
b0 )
b1110000000000000000000000000000 #
b1110000000000000000000000000000 &
#150000
0!
b1 "
b1 )
b1000 %
b1000 (
b1010 $
b1010 '
b1000 #
b1000 &
#160000
1!
b0 "
b0 )
b1000 $
b1000 '
#170000
b11110000000000000000000000000000 $
b11110000000000000000000000000000 '
#180000
0!
b1 "
b1 )
b1001 %
b1001 (
b1010 $
b1010 '
#190000
1!
b0 "
b0 )
b1000 $
b1000 '
#200000
0!
b1 "
b1 )
b11110000000000000000000000000000 $
b11110000000000000000000000000000 '
#210000
b1010 %
b1010 (
b1100 $
b1100 '
b1100 #
b1100 &
#220000
1!
b0 "
b0 )
b11110000000000000000000000000000 $
b11110000000000000000000000000000 '
b1000 #
b1000 &
#230000
0!
b1 "
b1 )
b1011 %
b1011 (
b1100011 $
b1100011 '
#240000
1!
b0 "
b0 )
b101010 $
b101010 '
b101010 #
b101010 &
#250000
b1100 %
b1100 (
b1010 $
b1010 '
b1000 #
b1000 &
#260000
0!
b1 "
b1 )
b1000 $
b1000 '
#270000
b11110000000000000000000000000000 $
b11110000000000000000000000000000 '
#280000
1!
b0 "
b0 )
b1101 %
b1101 (
b1010 $
b1010 '
#290000
0!
b1 "
b1 )
b1000 $
b1000 '
#300000
1!
b0 "
b0 )
b11110000000000000000000000000000 $
b11110000000000000000000000000000 '
