src/DataMemory.v
module data_memory (
    input clk,
    input we, //write enable
    input re, //read enable
    input sr, //SEXT vs ~ZEXT
    input [1:0] num_bytes, // 00 = 1 byte, 01 = 2 bytes, 3 bytes not used, 11 = 4 bytes
    input [31:0] addr,
    input [31:0] wdata,
    output reg [31:0] rdata
);
    // Smaller size for simulation
    reg [7:0] data_memory [0:255];

    always @(*) begin
        if(re) begin
            for(integer i = 0; i < 4; i++) begin
                if(i < (num_bytes+1))
                    rdata[i*8 +: 8] = data_memory[addr[7:0] + i];
                else if (sr)
                    rdata[i*8 +: 8] = {8{data_memory[addr[7:0] + num_bytes][7]}};
                else
                    rdata[i*8 +: 8] = 8'h00;
            end
        end
    end

    always @(posedge clk) begin
        if(we) begin
            for(integer i = 0; i < num_bytes; i++) begin
                data_memory[addr[7:0] + i] = wdata[i*8 +: 8];
            end
        end
    end

endmodule

tb/tb_DataMemory.v
`timescale 1ns/1ps

module tb_DataMemory;

    reg clk, we, re, sr;
    reg [1:0] num_bytes;
    reg [31:0] addr, wdata;

    wire [31:0] rdata;

    data_memory test_data_memory(
        .clk(clk),
        .we(we),
        .re(re),
        .sr(sr),
        .num_bytes(num_bytes),
        .addr(addr),
        .wdata(wdata),
        .rdata(rdata)
    );

    always #5 clk = ~clk;

    initial begin
        clk = 1'b0;
        we = 1'b0;
        re = 1'b0;
        num_bytes = 2'b11;

        $dumpfile("sim/data_memory.vcd");
        $dumpvars(0, tb_DataMemory);

        // simple write and then read
        we = 1'b1; addr = 32'd15; wdata = 32'd42;

        @(posedge clk);

        we = 1'b0; re = 1'b1;

        @(posedge clk);

        if(rdata != 32'd42)
            $display("FAIL DATAMEM WR: expected 42, got %d");
        else
            $display("PASS DATAMEM WR");

        re = 1'b0;

        repeat (15) @(posedge clk);

        // Retains value test
        re = 1'b1; 

        if(rdata != 32'd42)
            $display("FAIL DATAMEM RETAIN: expected 42, got %d");
        else
            $display("PASS DATAMEM RETAIN");

        re = 1'b0; 

        @(posedge clk);

        // Wrong read
        we = 1'b1; addr = 32'd42; wdata = 32'd67;

        @(posedge clk);

        we = 1'b0; re = 1'b0;

        @(posedge clk);

        if(rdata != 32'd42)
            $display("FAIL DATAMEM R1: expected 42, got %d");
        else
            $display("PASS DATAMEM R1");

        re = 1'b0;

        @(posedge clk);

        re = 1'b1;

        @(posedge clk);

        if(rdata != 32'd67)
            $display("FAIL DATAMEM R2: expected 67, got %d");
        else
            $display("PASS DATAMEM R2");

        re = 1'b0;

        @(posedge clk);

        // wrong write
        we = 1'b0; addr = 32'd15; wdata = 32'd100;

        @(posedge clk);

        we = 1'b0; re = 1'b0;

        @(posedge clk);

        if(rdata != 32'd42)
            $display("FAIL DATAMEM W: expected 42, got %d");
        else
            $display("PASS DATAMEM W");

        re = 1'b0;

        @(posedge clk);

        //testing SEXT and ZEXT
        we = 1'b1; addr = 32'd2; wdata = 8'hFF; num_bytes = 2'b00; sr = 1'b1; //1 byte

        @(posedge clk);

        we = 1'b0; re = 1'b1;

        @(posedge clk);

        if(rdata != -32'd1)
            $display("FAIL DATAMEM SEXT: expected -1, got %d");
        else
            $display("PASS DATAMEM SEXT");

        re = 1'b0; sr = 1'b0;

        @(posedge clk);

        re = 1'b1;

        @(posedge clk);

        if(rdata != 32'd255)
            $display("FAIL DATAMEM ZEXT: expected 255, got %d");
        else
            $display("PASS DATAMEM ZEXT");



        $finish;
    end


endmodule

sim/data_memory.vcd
$date
	Sat Jun  6 21:49:38 2026
$end
$version
	Icarus Verilog
$end
$timescale
	1ps
$end
$scope module tb_DataMemory $end
$var wire 32 ! rdata [31:0] $end
$var reg 32 " addr [31:0] $end
$var reg 1 # clk $end
$var reg 2 $ num_bytes [1:0] $end
$var reg 1 % re $end
$var reg 1 & sr $end
$var reg 32 ' wdata [31:0] $end
$var reg 1 ( we $end
$scope module test_data_memory $end
$var wire 32 ) addr [31:0] $end
$var wire 1 # clk $end
$var wire 2 * num_bytes [1:0] $end
$var wire 1 % re $end
$var wire 1 & sr $end
$var wire 32 + wdata [31:0] $end
$var wire 1 ( we $end
$var reg 32 , rdata [31:0] $end
$scope begin $ivl_for_loop0 $end
$var integer 32 - i [31:0] $end
$upscope $end
$scope begin $ivl_for_loop1 $end
$var integer 32 . i [31:0] $end
$upscope $end
$upscope $end
$upscope $end
$enddefinitions $end
$comment Show the parameter values. $end
$dumpall
$end
#0
$dumpvars
bx .
bx -
bx ,
b101010 +
b11 *
b1111 )
1(
b101010 '
x&
0%
b11 $
0#
b1111 "
bx !
$end
#5000
b100 -
1%
0(
1#
#10000
0#
#15000
0%
1#
#20000
0#
#25000
1#
#30000
0#
#35000
1#
#40000
0#
#45000
1#
#50000
0#
#55000
1#
#60000
0#
#65000
1#
#70000
0#
#75000
1#
#80000
0#
#85000
1#
#90000
0#
#95000
1#
#100000
0#
#105000
1#
#110000
0#
#115000
1#
#120000
0#
#125000
1#
#130000
0#
#135000
1#
#140000
0#
#145000
1#
#150000
0#
#155000
1#
#160000
0#
#165000
0%
1#
#170000
0#
#175000
b1000011 '
b1000011 +
b101010 "
b101010 )
1(
1#
#180000
0#
#185000
0(
1#
#190000
0#
#195000
1#
#200000
0#
#205000
b100 -
1%
1#
#210000
0#
#215000
0%
1#
#220000
0#
#225000
b1100100 '
b1100100 +
b1111 "
b1111 )
1#
#230000
0#
#235000
1#
#240000
0#
#245000
1#
#250000
0#
#255000
1&
b0 $
b0 *
b11111111 '
b11111111 +
b10 "
b10 )
1(
1#
#260000
0#
#265000
b100 -
1%
0(
1#
#270000
0#
#275000
0&
0%
1#
#280000
0#
#285000
b0xxxxxxxx !
b0xxxxxxxx ,
b100 -
1%
1#
