src/MUX.v
module mux #(
    parameter DATA_WIDTH = 32,
    parameter INPUT_WIDTH = 2,
    parameter SELECT_BITS = 1
) (
    input [(INPUT_WIDTH*DATA_WIDTH)-1:0] data_in,
    input [SELECT_BITS-1:0] sel,
    output [DATA_WIDTH-1:0] out
);

    assign out = data_in[sel*(DATA_WIDTH) +: DATA_WIDTH];

endmodule

tb/tb_MUX.v
`timescale 1ns/1ps

module tb_MUX;

    reg [15:0] in1, in2, in3, in4;
    reg [2:0] in33, in32, in31;
    reg [1:0] sel, sel3;

    wire [15:0] out2, out4;
    wire [2:0] out3;

    mux #(.DATA_WIDTH(16), .INPUT_WIDTH(2), .SELECT_BITS(1)) test_mux_2 (
        .data_in({in2, in1}),
        .sel(sel[0]),
        .out(out2)
    );
    mux #(.DATA_WIDTH(16), .INPUT_WIDTH(4), .SELECT_BITS(2)) test_mux_4 (
        .data_in({in4, in3, in2, in1}),
        .sel(sel),
        .out(out4)
    );

    mux #(.DATA_WIDTH(3), .INPUT_WIDTH(3), .SELECT_BITS(2)) test_mux_3 (
        .data_in({in33, in32, in31}),
        .sel(sel),
        .out(out3)
    );


    initial begin
        $dumpfile("sim/mux.vcd");
        $dumpvars(0, tb_MUX);

        //initialization
        in1 = 16'd42; in2 = 16'd0; in3 = 16'd1; in4 = 16'd7;
        in33 = 3'd0; in32 = 3'd7; in31 = 3'd2;

        // 2 16-bit input (1 select bit)
        sel[0] = 1'b0;
        #10;
        if (out2 != 16'd42)
            $display("FAIL MUX2 1: expected 42, got %0d", out2);
        else   
            $display("PASS MUX2 1");

        sel[0] = 1'b1;
        #10;
        if (out2 != 16'd0)
            $display("FAIL MUX2 2: expected 0, got %0d", out2);
        else   
            $display("PASS MUX2 2");

        // 4 16-bit input (2 select bits)
        sel = 2'b00;
        #10;
        if (out4 != 16'd42)
            $display("FAIL MUX4 1: expected 42, got %0d", out4);
        else   
            $display("PASS MUX4 1");

        sel = 2'b01;
        #10;
        if (out4 != 16'd0)
            $display("FAIL MUX4 2: expected 0, got %0d", out4);
        else   
            $display("PASS MUX4 2");

        sel = 2'b10;
        #10;
        if (out4 != 16'd1)
            $display("FAIL MUX4 3: expected 1, got %0d", out4);
        else   
            $display("PASS MUX4 3");

        sel = 2'b11;
        #10;
        if (out4 != 16'd7)
            $display("FAIL MUX4 4: expected 7, got %0d", out4);
        else   
            $display("PASS MUX4 4");

        // 3 3-bit input (2 select bits)
        sel3 = 2'b00;
        #10;
        if (out3 != 3'd2)
            $display("FAIL MUX3 1: expected 2, got %0d", out4);
        else   
            $display("PASS MUX3 1");

        sel3 = 2'b01;
        #10;
        if (out3 != 3'd7)
            $display("FAIL MUX3 2: expected 7, got %0d", out4);
        else   
            $display("PASS MUX3 2");

        sel3 = 2'b10;
        #10;
        if (out3 != 3'd0)
            $display("FAIL MUX3 3: expected 0, got %0d", out4);
        else   
            $display("PASS MUX3 3");

        $finish;
    end

endmodule

sim/mux.vcd
$date
	Tue Jun  9 22:39:31 2026
$end
$version
	Icarus Verilog
$end
$timescale
	1ps
$end
$scope module tb_MUX $end
$var wire 16 ! out4 [15:0] $end
$var wire 3 " out3 [2:0] $end
$var wire 16 # out2 [15:0] $end
$var reg 16 $ in1 [15:0] $end
$var reg 16 % in2 [15:0] $end
$var reg 16 & in3 [15:0] $end
$var reg 3 ' in31 [2:0] $end
$var reg 3 ( in32 [2:0] $end
$var reg 3 ) in33 [2:0] $end
$var reg 16 * in4 [15:0] $end
$var reg 2 + sel [1:0] $end
$var reg 2 , sel3 [1:0] $end
$scope module test_mux_2 $end
$var wire 32 - data_in [31:0] $end
$var wire 1 . sel $end
$var wire 16 / out [15:0] $end
$var parameter 32 0 DATA_WIDTH $end
$var parameter 32 1 INPUT_WIDTH $end
$var parameter 32 2 SELECT_BITS $end
$upscope $end
$scope module test_mux_3 $end
$var wire 9 3 data_in [8:0] $end
$var wire 2 4 sel [1:0] $end
$var wire 3 5 out [2:0] $end
$var parameter 32 6 DATA_WIDTH $end
$var parameter 32 7 INPUT_WIDTH $end
$var parameter 32 8 SELECT_BITS $end
$upscope $end
$scope module test_mux_4 $end
$var wire 64 9 data_in [63:0] $end
$var wire 2 : sel [1:0] $end
$var wire 16 ; out [15:0] $end
$var parameter 32 < DATA_WIDTH $end
$var parameter 32 = INPUT_WIDTH $end
$var parameter 32 > SELECT_BITS $end
$upscope $end
$upscope $end
$enddefinitions $end
$comment Show the parameter values. $end
$dumpall
b10 >
b100 =
b10000 <
b10 8
b11 7
b11 6
b1 2
b10 1
b10000 0
$end
#0
$dumpvars
bx ;
bx0 :
b111000000000000000100000000000000000000000000101010 9
bx 5
bx0 4
b111010 3
b101010 /
0.
b101010 -
bx ,
bx0 +
b111 *
b0 )
b111 (
b10 '
b1 &
b0 %
b101010 $
b101010 #
bx "
bx !
$end
#10000
b0 #
b0 /
1.
bx1 +
bx1 4
bx1 :
#20000
b101010 #
b101010 /
0.
b10 "
b10 5
b101010 !
b101010 ;
b0 +
b0 4
b0 :
#30000
b0 #
b0 /
1.
b111 "
b111 5
b0 !
b0 ;
b1 +
b1 4
b1 :
#40000
b101010 #
b101010 /
0.
b0 "
b0 5
b1 !
b1 ;
b10 +
b10 4
b10 :
#50000
b0 #
b0 /
1.
bx "
bx 5
b111 !
b111 ;
b11 +
b11 4
b11 :
#60000
b0 ,
#70000
b1 ,
#80000
b10 ,
