src/RegisterFile.v

module register_file(
    input clk, 
    input we,
    input [4:0] raddr1, //address to read from
    input [4:0] raddr2, //32 registers so 5 bits
    input [4:0] waddr, //address to write to
    input [31:0] wdata, //data to write
    output [31:0] rdata1, //data read
    output [31:0] rdata2
);

    //32 registers
    //not really gonna use the first one, but complicates to remove it
    reg [31:0] register [31:0];

    //read
    //async for single cycle reasons
    //turnary operator is used since we don't know the initial state of register[0]
    assign rdata1 = (raddr1 == 5'd0) ? 32'd0 : register[raddr1];
    assign rdata2 = (raddr2 == 5'd0) ? 32'd0 : register[raddr2];

    //write
    always @(posedge clk) begin
        if(we && (waddr != 5'd0))
            register[waddr] <= wdata;
    end

endmodule

src/ImmediateGenerator.v
module immediate_generator (
    input [31:0] data_in,
    output reg [31:0] data_out
);

always @(*) begin
    data_out = 32'd0;
    case(data_in[6:0])
        //I-type
        7'b0010011, 7'b0000011, 7'b1100111: begin
            data_out = {{21{data_in[31]}}, data_in[30:20]};
        end
        //S-Type
        7'b0100011: begin
            data_out = {{21{data_in[31]}}, data_in[30:25], data_in[11:7]};
        end
        //B-Type
        7'b1100011: begin
            data_out = {{20{data_in[31]}}, data_in[7], data_in[30:25], data_in[11:8], 1'b0};
        end
        //U-Type
        7'b0110111, 7'b0010111: begin
            data_out = {data_in[31:12], 12'd0};
        end
        //J-Type
        7'b1101111: begin
            data_out = {{12{data_in[31]}}, data_in[19:12], data_in[20], data_in[30:21], 1'b0};
        end

        default: data_out = 32'd0;
    endcase
end


endmodule

src/IF_ID.v
module if_id (
    input clk,
    input FLUSH_E,
    input reset,
    input [31:0] PCF,
    input [31:0] InstrF,
    input [31:0] PCPlus4F,
    output reg [31:0] PCD,
    output reg [31:0] InstrD,
    output reg [31:0] PCPlus4D
);

    always @(posedge clk) begin
        if(reset | FLUSH_E) begin
            PCD <= 32'd0;
            InstrD <= 32'd0;
            PCPlus4D <= 32'd0;
        end
        else begin
            PCD <= PCF;
            InstrD <= InstrF;
            PCPlus4D <= PCPlus4F;
        end

    end

endmodule

src/MUX.v
module mux #(
    parameter DATA_WIDTH = 32,
    parameter INPUT_WIDTH = 2,
    parameter SELECT_BITS = 1
) (
    input [(INPUT_WIDTH*DATA_WIDTH)-1:0] data_in,
    input [SELECT_BITS-1:0] sel,
    output [DATA_WIDTH-1:0] out
);

    assign out = data_in[sel*(DATA_WIDTH) +: DATA_WIDTH];

endmodule

src/ALU.v
module alu (
    input [31:0] a,
    input [31:0] b,
    input [3:0] sel,
    output reg [31:0] s,
    output zero
    );

    assign zero = (s == 32'd0);

    always @(*) begin
        case(sel)
            4'd0: s = a + b; //add
            4'd1: s = a - b; //sub
            4'd2: s = a ^ b; //xor
            4'd3: s = a | b; //or
            4'd4: s = a & b; //and
            4'd5: s = a << b[4:0]; //sll
            4'd6: s = a >> b[4:0]; //srl
            4'd7: s = $signed(a) >>> b[4:0]; //sra
            4'd8: s = ($signed(a) < $signed(b)) ? 1 : 0; //slt
            4'd9: s = ($unsigned(a) < $unsigned(b)) ? 1 : 0; //sltu
            4'd10: s = (a == b) ? 1 : 0; //beq
            4'd11: s = (a != b) ? 1 : 0; //bne
            4'd12: s = ($signed(a) >= $signed(b)) ? 1 : 0; //bge
            4'd13: s = ($unsigned(a) >= $unsigned(b)) ? 1 : 0; //bgeu
            4'd14: s = 32'd1; //For unconditional jumpsS 
            default: s = 32'd0;
        endcase
    end
endmodule

src/InstructionMemory.v
module instruction_memory (
    input  [31:0] raddr,
    output [31:0] instr
);

    // Smaller size for simulation
    reg [7:0] instruction_memory [0:1023];

    // Load program
    initial begin
        $readmemh("prog/nh_pipelined_test_branch.hex", instruction_memory, 8'd0);
    end

    //using 32-bit word size, but using the higher bits of pc
    assign instr = {instruction_memory[raddr[9:0]], instruction_memory[raddr[9:0]+1], instruction_memory[raddr[9:0]+2], instruction_memory[raddr[7:0]+3]};

endmodule

src/ProgramCounter.v
module program_counter (
    input clk,
    input reset,
    input [31:0] wdata,
    output [31:0] rdata
);
    reg [31:0] program_counter;

    assign rdata = program_counter;

    always @(posedge clk) begin
        if(reset)
            program_counter = 32'd0;
        else
            program_counter <= wdata;
    end

endmodule

src/Pipelined_CPU.v
module p_cpu (input clk, input reset);

    // ==================== WIRES ====================

    // INSTRUCION FETCH
    wire [31:0] PCMUX_OUT, PCF, WIRED4_F, InstrF, PCPlus4F;

    // INSTRUCTION DECODE
    wire [31:0] PCD, InstrD, PCPlus4D, ImmD, RS1D, RS2D;
    wire [1:0] REG_MUX_D;
    wire REG_EN_D;
    wire WE_D;
    wire SZ_D;
    wire [1:0] NUM_BYTES_D;
    wire JUMP_D;
    wire JALR_D;
    wire [3:0] ALU_SEL_D;
    wire ALUMUX1_D;
    wire ALUMUX2_D;
    wire BR_EN_D;

    // EXECUTE
    wire [31:0] PCE, ImmE, RS1E, RS2E, PCPlus4E, PCPlusImmE, ALUE, ALUMUX1_OUT, ALUMUX2_OUT, JALRMUX_OUT, CTAddrE, InstrE;
    wire FLUSH_E;
    wire [1:0] REG_MUX_E;
    wire REG_EN_E;
    wire WE_E;
    wire SZ_E;
    wire [1:0] NUM_BYTES_E;
    wire JUMP_E;
    wire JALR_E;
    wire [3:0] ALU_SEL_E;
    wire ALUMUX1_E;
    wire ALUMUX2_E;
    wire BR_EN_E;

    // MEMORY
    wire [31:0] ImmM, ALUM, RS2M, PCPlus4M, MEMM, InstrM;
    wire [1:0] REG_MUX_M;
    wire REG_EN_M;
    wire WE_M;
    wire SZ_M;
    wire [1:0] NUM_BYTES_M;

    // WRITEBACK
    wire [31:0] ImmW, ALUW, MEMW, PCPlus4W, WBDataW, InstrW;
    wire [1:0] REG_MUX_W; 
    wire REG_EN_W;

    assign WIRED4_F = 32'd4;

    //pUT THIS INTO EXECUTE
    assign FLUSH_E = JUMP_E | (BR_EN_E & ALUE[0]);

    // ==================== MODULES ====================

    // iNSTRUCTION FETCH
    program_counter program_counter (
        .clk(clk),
        .reset(reset),
        .wdata(PCMUX_OUT),
        .rdata(PCF)
    );

    instruction_memory instruction_memory (
        .raddr(PCF),
        .instr(InstrF)
    );

    alu pc_plus_4 (
        .a(PCF),
        .b(WIRED4_F),
        .sel(4'd0),
        .s(PCPlus4F)
    );

    mux #(.DATA_WIDTH(32), .INPUT_WIDTH(2), .SELECT_BITS(1)) pcmux (
        .data_in({CTAddrE, PCPlus4F}),
        .sel(FLUSH_E),
        .out(PCMUX_OUT)
    );

    // IF/ID REGISTER

    if_id if_id (
        .clk(clk),
        .FLUSH_E(FLUSH_E),
        .reset(reset),
        .PCF(PCF),
        .InstrF(InstrF),
        .PCPlus4F(PCPlus4F),
        .PCD(PCD),
        .InstrD(InstrD),
        .PCPlus4D(PCPlus4D)
    );

    // INSTRUCTION DECODE

    immediate_generator immediate_generator (
        .data_in(InstrD),
        .data_out(ImmD)
    );

    register_file register_file(
        .clk(clk),
        .we(REG_EN_W),
        .raddr1(InstrD[19:15]),
        .raddr2(InstrD[24:20]),
        .waddr(InstrW[11:7]),
        .wdata(WBDataW),
        .rdata1(RS1D),
        .raddr2(RS2D)
    );




endmodule

tb/TB_Pipelined_CPU_NH/NH_Branch.v
`timescale 1ns/1ps

module NH_Branch;

    reg clk;
    reg reset;

    reg [31:0] expected [0:31];
    integer i;
    integer errors;

    initial begin
        expected[0] = 32'h00000000;
        expected[1] = 32'h00000000;
        expected[2] = 32'h00002001;
        expected[3] = 32'h00003002;
        expected[4] = 32'h00004003;
        expected[5] = 32'h00005004;
        expected[6] = 32'h00000005;
        expected[7] = 32'h00000006;
        expected[8] = 32'h00000007;
        expected[9] = 32'h00000008;
    end

    p_cpu test_cpu (.clk(clk), .reset(reset));

    always #5 clk = ~clk;

    initial begin
        clk = 1'b0;

        $dumpfile("sim/nh_branch.vcd");
        $dumpvars(1, NH_Branch, NH_Branch.test_cpu);

        reset = 1'b1;

        @(posedge clk); #1;

        reset = 1'b0;

        repeat(100) @(posedge clk);

        errors = 0;

        for (i = 0; i < 12; i = i + 1) begin
            if (test_cpu.register_file.register[i] !== expected[i]) begin
                errors = errors + 1;
                $display("FAIL AT R%0d: expected %08h, got %08h",
                        i,
                        expected[i],
                        test_cpu.register_file.register[i]);
            end
        end

        if (errors == 0)
            $display("PASS: Pipelined Branch test");
        else
            $display("FAIL: %0d register mismatches", errors);

        $finish;

    end

endmodule

sim/nh_branch.vcd
$date
	Fri Jun 19 02:47:50 2026
$end
$version
	Icarus Verilog
$end
$timescale
	1ps
$end
$scope module NH_Branch $end
$var reg 1 ! clk $end
$var reg 1 " reset $end
$var integer 32 # errors [31:0] $end
$var integer 32 $ i [31:0] $end
$upscope $end
$scope module NH_Branch $end
$scope module test_cpu $end
$var wire 1 % FLUSH_E $end
$var wire 32 & WIRED4_F [31:0] $end
$var wire 1 ! clk $end
$var wire 1 " reset $end
$var wire 1 ' WE_M $end
$var wire 1 ( WE_E $end
$var wire 1 ) WE_D $end
$var wire 32 * WBDataW [31:0] $end
$var wire 1 + SZ_M $end
$var wire 1 , SZ_E $end
$var wire 1 - SZ_D $end
$var wire 32 . RS2M [31:0] $end
$var wire 32 / RS2E [31:0] $end
$var wire 32 0 RS2D [31:0] $end
$var wire 32 1 RS1E [31:0] $end
$var wire 32 2 RS1D [31:0] $end
$var wire 2 3 REG_MUX_W [1:0] $end
$var wire 2 4 REG_MUX_M [1:0] $end
$var wire 2 5 REG_MUX_E [1:0] $end
$var wire 2 6 REG_MUX_D [1:0] $end
$var wire 1 7 REG_EN_W $end
$var wire 1 8 REG_EN_M $end
$var wire 1 9 REG_EN_E $end
$var wire 1 : REG_EN_D $end
$var wire 32 ; PCPlusImmE [31:0] $end
$var wire 32 < PCPlus4W [31:0] $end
$var wire 32 = PCPlus4M [31:0] $end
$var wire 32 > PCPlus4F [31:0] $end
$var wire 32 ? PCPlus4E [31:0] $end
$var wire 32 @ PCPlus4D [31:0] $end
$var wire 32 A PCMUX_OUT [31:0] $end
$var wire 32 B PCF [31:0] $end
$var wire 32 C PCE [31:0] $end
$var wire 32 D PCD [31:0] $end
$var wire 2 E NUM_BYTES_M [1:0] $end
$var wire 2 F NUM_BYTES_E [1:0] $end
$var wire 2 G NUM_BYTES_D [1:0] $end
$var wire 32 H MEMW [31:0] $end
$var wire 32 I MEMM [31:0] $end
$var wire 1 J JUMP_E $end
$var wire 1 K JUMP_D $end
$var wire 1 L JALR_E $end
$var wire 1 M JALR_D $end
$var wire 32 N JALRMUX_OUT [31:0] $end
$var wire 32 O InstrW [31:0] $end
$var wire 32 P InstrM [31:0] $end
$var wire 32 Q InstrF [31:0] $end
$var wire 32 R InstrE [31:0] $end
$var wire 32 S InstrD [31:0] $end
$var wire 32 T ImmW [31:0] $end
$var wire 32 U ImmM [31:0] $end
$var wire 32 V ImmE [31:0] $end
$var wire 32 W ImmD [31:0] $end
$var wire 32 X CTAddrE [31:0] $end
$var wire 1 Y BR_EN_E $end
$var wire 1 Z BR_EN_D $end
$var wire 4 [ ALU_SEL_E [3:0] $end
$var wire 4 \ ALU_SEL_D [3:0] $end
$var wire 32 ] ALUW [31:0] $end
$var wire 32 ^ ALUMUX2_OUT [31:0] $end
$var wire 1 _ ALUMUX2_E $end
$var wire 1 ` ALUMUX2_D $end
$var wire 32 a ALUMUX1_OUT [31:0] $end
$var wire 1 b ALUMUX1_E $end
$var wire 1 c ALUMUX1_D $end
$var wire 32 d ALUM [31:0] $end
$var wire 32 e ALUE [31:0] $end
$upscope $end
$upscope $end
$enddefinitions $end
$comment Show the parameter values. $end
$dumpall
$end
#0
$dumpvars
bx e
bx d
xc
xb
bx a
x`
x_
bx ^
bx ]
bx \
bx [
xZ
xY
bx X
bx W
bx V
bx U
bx T
bx S
bx R
bx Q
bx P
bx O
bx N
xM
xL
xK
xJ
bx I
bx H
bx G
bx F
bx E
bx D
bx C
bx B
bx A
bx @
bx ?
bx >
bx =
bx <
bx ;
x:
x9
x8
x7
bx 6
bx 5
bx 4
bx 3
bx 2
bx 1
bx 0
bx /
bx .
x-
x,
x+
bx *
x)
x(
x'
b100 &
x%
bx $
bx #
1"
0!
$end
#5000
b0 G
0-
0)
0M
0Z
0K
b0 \
0`
0c
b0 6
0:
b0 0
b0 2
b100 A
0%
b0 W
b0 N
b0 e
b0 X
b0 ;
b0xxxxxxxx I
b0 @
b0 S
b0 D
0Y
b0 ^
0_
b0 a
0b
b0 [
0L
0J
b0 F
0,
0(
09
b0 5
b0 R
b0 ?
b0 /
b0 1
b0 V
b0 C
b0 E
0+
0'
08
b0 4
b0 P
b0 =
b0 .
b0 d
b0 U
07
b0 *
b0 3
b0 O
b0 <
b0 H
b0 ]
b0 T
b1000010110111 Q
b100 >
b0 B
1!
#6000
0"
#10000
0!
#15000
b11 6
1:
b1000000000000 W
b10000100110111 Q
b1000 A
b1000 >
b0xxxxxxxx H
b100 @
b1000010110111 S
b100 B
1!
#20000
0!
#25000
b11000110110111 Q
b1100 A
b1100 >
b10000000000000 W
b1000000000000 X
b1000000000000 ;
b1000 B
b1000 @
b10000100110111 S
b100 D
19
b11 5
b1000010110111 R
b100 ?
b1000000000000 V
1!
#30000
0!
#35000
b10000000000100 X
b10000000000100 ;
b100 N
b100 e
b11000000000000 W
b100001000110111 Q
b10000 A
b10000 >
18
b11 4
b1000010110111 P
b100 =
b1000000000000 U
b10000100110111 R
b1000 ?
b10000000000000 V
b100 a
b100 C
b1100 @
b11000110110111 S
b1000 D
b1100 B
1!
#40000
0!
#45000
b101001010110111 Q
b10100 A
b10100 >
b100000000000000 W
b11000000001000 X
b11000000001000 ;
b1000 N
b1000 e
b10000 B
b10000 @
b100001000110111 S
b1100 D
b11000110110111 R
b1100 ?
b11000000000000 V
b1000 a
b1000 C
b10000100110111 P
b1000 =
b100 d
b10000000000000 U
17
b11 3
b1000010110111 O
b1000000000000 *
b100 <
b1000000000000 T
1!
#50000
0!
#55000
b100000000001100 X
b100000000001100 ;
b1100 N
b1100 e
b101000000000000 W
b1100110111 Q
b11000 A
b11000 >
b10000100110111 O
b1000 <
b100 ]
b10000000000000 *
b10000000000000 T
b11000110110111 P
b1100 =
b1000 d
b11000000000000 U
b100001000110111 R
b10000 ?
b100000000000000 V
b1100 a
b1100 C
b10100 @
b101001010110111 S
b10000 D
b10100 B
1!
#60000
0!
#65000
b1110110111 Q
b11100 A
b11100 >
b0 W
b101000000010000 X
b101000000010000 ;
b10000 N
b10000 e
b11000 B
b11000 @
b1100110111 S
b10100 D
b101001010110111 R
b10100 ?
b101000000000000 V
b10000 a
b10000 C
b100001000110111 P
b10000 =
b1100 d
b100000000000000 U
b11000110110111 O
b1100 <
b1000 ]
b11000000000000 *
b11000000000000 T
1!
#70000
0!
#75000
b10100 X
b10100 ;
b10100 N
b10100 e
b10000110111 Q
b100000 A
b100000 >
b100001000110111 O
b10000 <
b1100 ]
b100000000000000 *
b100000000000000 T
b101001010110111 P
b10100 =
b10000 d
b101000000000000 U
b1100110111 R
b11000 ?
b0 V
b10100 a
b10100 C
b11100 @
b1110110111 S
b11000 D
b11100 B
1!
#80000
0!
#85000
b10010110111 Q
b100100 A
b100100 >
b11000 X
b11000 ;
b11000 N
b11000 e
b100000 B
b100000 @
b10000110111 S
b11100 D
b1110110111 R
b11100 ?
b11000 a
b11000 C
b1100110111 P
b11000 =
b10100 d
b0 U
b101001010110111 O
b10100 <
b10000 ]
b101000000000000 *
b101000000000000 T
1!
#90000
0!
#95000
b11100 X
b11100 ;
b11100 N
b11100 e
b100001000000010010011 Q
b101000 A
b101000 >
b1100110111 O
b11000 <
b10100 ]
b0 *
b0 T
b1110110111 P
b11100 =
b11000 d
b10000110111 R
b100000 ?
b11100 a
b11100 C
b100100 @
b10010110111 S
b100000 D
b100100 B
1!
#100000
0!
#105000
1`
1c
b1 6
b1000000000000 0
b1000000000000 2
b100010000000100010011 Q
b101100 A
b101100 >
b1 W
b100000 X
b100000 ;
b100000 N
b100000 e
b101000 B
b101000 @
b100001000000010010011 S
b100100 D
b10010110111 R
b100100 ?
b100000 a
b100000 C
b10000110111 P
b100000 =
b11100 d
b1110110111 O
b11100 <
b11000 ]
1!
#110000
0!
#115000
b10000000000000 2
b100101 X
b100101 ;
b1000000000001 N
b1000000000001 e
b1 W
b1000011000000110010011 Q
b110000 A
b110000 >
b10000110111 O
b100000 <
b11100 ]
b10010110111 P
b100100 =
b100000 d
1_
1b
b1 5
b100001000000010010011 R
b101000 ?
b1 ^
b1000000000000 /
b1000000000000 1
b1 V
b1000000000000 a
b100100 C
b101100 @
b100010000000100010011 S
b101000 D
b101100 B
1!
#120000
0!
#125000
b10000000000000 0
b11000000000000 2
b1100100000001000010011 Q
b110100 A
b110100 >
b10 W
b10000000000001 N
b10000000000001 e
b101001 X
b101001 ;
b110000 B
b110000 @
b1000011000000110010011 S
b101100 D
b100010000000100010011 R
b101100 ?
b10000000000000 a
b10000000000000 1
b101000 C
b1 4
b100001000000010010011 P
b101000 =
b1000000000000 .
b1000000000001 d
b1 U
b10010110111 O
b100100 <
b100000 ]
1!
#130000
0!
#135000
b11000000000000 0
b100000000000000 2
b11000000000010 N
b11000000000010 e
b101110 X
b101110 ;
b11 W
b10000101000001010010011 Q
b111000 A
b111000 >
b1 3
b100001000000010010011 O
b101000 <
b1000000000001 ]
b1000000000001 *
b1 T
b100010000000100010011 P
b101100 =
b10000000000001 d
b1000011000000110010011 R
b110000 ?
b10000000000000 /
b11000000000000 a
b11000000000000 1
b10 ^
b10 V
b101100 C
b110100 @
b1100100000001000010011 S
b110000 D
b110100 B
1!
#140000
0!
#145000
b100000000000000 0
b101000000000000 2
b10100110000001100010011 Q
b111100 A
b111100 >
b100 W
b100000000000011 N
b100000000000011 e
b110011 X
b110011 ;
b111000 B
b111000 @
b10000101000001010010011 S
b110100 D
b1100100000001000010011 R
b110100 ?
b11000000000000 /
b100000000000000 a
b100000000000000 1
b11 ^
b11 V
b110000 C
b1000011000000110010011 P
b110000 =
b10000000000000 .
b11000000000010 d
b10 U
b100010000000100010011 O
b101100 <
b10000000000001 *
b10000000000001 ]
1!
#150000
0!
#155000
b101000000000000 0
b0 2
b101000000000100 N
b101000000000100 e
b111000 X
b111000 ;
b101 W
b11000111000001110010011 Q
b1000000 A
b1000000 >
b1000011000000110010011 O
b110000 <
b11000000000010 *
b11000000000010 ]
b10 T
b1100100000001000010011 P
b110100 =
b11000000000000 .
b100000000000011 d
b11 U
b10000101000001010010011 R
b111000 ?
b100000000000000 /
b101000000000000 a
b101000000000000 1
b100 ^
b100 V
b110100 C
b111100 @
b10100110000001100010011 S
b111000 D
b111100 B
1!
#160000
0!
#165000
b0 0
b11101000000010000010011 Q
b1000100 A
b1000100 >
b110 W
b101 N
b101 e
b111101 X
b111101 ;
b1000000 B
b1000000 @
b11000111000001110010011 S
b111100 D
b10100110000001100010011 R
b111100 ?
b101000000000000 /
b0 a
b0 1
b101 ^
b101 V
b111000 C
b10000101000001010010011 P
b111000 =
b100000000000000 .
b101000000000100 d
b100 U
b1100100000001000010011 O
b110100 <
b100000000000011 *
b100000000000011 ]
b11 T
1!
#170000
0!
#175000
b110 N
b110 e
b1000010 X
b1000010 ;
b111 W
b100001001000010010010011 Q
b1001000 A
b1001000 >
b10000101000001010010011 O
b111000 <
b101000000000100 *
b101000000000100 ]
b100 T
b10100110000001100010011 P
b111100 =
b101000000000000 .
b101 d
b101 U
b11000111000001110010011 R
b1000000 ?
b0 /
b110 ^
b110 V
b111100 C
b1000100 @
b11101000000010000010011 S
b1000000 D
b1000100 B
1!
#180000
0!
#185000
b1000001000010001100011 Q
b1001100 A
b1001100 >
b1000 W
b111 N
b111 e
b1000111 X
b1000111 ;
b1001000 B
b1001000 @
b100001001000010010010011 S
b1000100 D
b11101000000010000010011 R
b1000100 ?
b111 ^
b111 V
b1000000 C
b11000111000001110010011 P
b1000000 =
b0 .
b110 d
b110 U
b10100110000001100010011 O
b111100 <
b101 *
b101 ]
b101 T
1!
#190000
0!
#195000
b1010 \
1Z
0`
b0 6
0:
b10000000000001 0
b1000000000001 2
b1000 N
b1000 e
b1001100 X
b1001100 ;
b1000 W
b10110111 Q
b1010000 A
b1010000 >
b11000111000001110010011 O
b1000000 <
b110 *
b110 ]
b110 T
b11101000000010000010011 P
b1000100 =
b111 d
b111 U
b100001001000010010010011 R
b1001000 ?
b1000 ^
b1000 V
b1000100 C
b1001100 @
b1000001000010001100011 S
b1001000 D
b1001100 B
1!
#200000
0!
#205000
0Z
b0 \
0c
b11 6
1:
b0 0
b0 2
b1100001001010001100011 Q
b1010100 A
b1010100 >
b0 W
b0 N
b0 e
b1010000 X
b1010000 ;
b1010000 B
b1010000 @
b10110111 S
b1001100 D
1Y
b10000000000001 ^
0_
b1010 [
09
b0 5
b1000001000010001100011 R
b1001100 ?
b10000000000001 /
b1000000000001 a
b1000000000001 1
b1001000 C
b100001001000010010010011 P
b1001000 =
b1000 d
b1000 U
b11101000000010000010011 O
b1000100 <
b111 *
b111 ]
b111 T
1!
#210000
0!
#215000
b1011 \
1Z
1c
b0 6
0:
b11000000000010 0
b1000000000001 2
b1001100 N
b1001100 e
b1001100 X
b1001100 ;
b1000 W
b100110111 Q
b1011000 A
b1011000 >
b100001001000010010010011 O
b1001000 <
b1000 *
b1000 ]
b1000 T
08
b0 4
b1000001000010001100011 P
b1001100 =
b10000000000001 .
b0 d
0Y
0b
b0 [
19
b11 5
b10110111 R
b1010000 ?
b0 ^
b0 /
b1001100 a
b0 1
b0 V
b1001100 C
b1010100 @
b1100001001010001100011 S
b1010000 D
b1010100 B
1!
#220000
0!
#225000
1%
0Z
b0 \
0c
b11 6
1:
b0 0
b0 2
b1100001100010001100011 Q
b1011000 A
b1011100 >
b0 W
b1011000 X
b1011000 ;
b1 N
b1 e
b1011000 B
b1011000 @
b100110111 S
b1010100 D
1Y
1b
b1011 [
09
b0 5
b1100001001010001100011 R
b1010100 ?
b11000000000010 ^
b11000000000010 /
b1000000000001 1
b1000 V
b1000000000001 a
b1010000 C
18
b11 4
b10110111 P
b1010000 =
b0 .
b1001100 d
b0 U
07
b0 3
b1000001000010001100011 O
b1001100 <
b1001100 *
b0 ]
1!
#230000
0!
#235000
0%
b0 6
0:
b0 N
b0 e
b1011100 A
b0 X
b0 ;
17
b11 3
b10110111 O
b0 *
b1010000 <
b1001100 ]
b0 T
08
b0 4
b1100001001010001100011 P
b1010100 =
b11000000000010 .
b1 d
b1000 U
0Y
0b
b0 [
b0 R
b0 ?
b0 ^
b0 /
b0 a
b0 1
b0 V
b0 C
b0 @
b0 S
b0 D
1!
#240000
0!
#245000
b1000 \
1Z
1c
b11000000000010 0
b110110111 Q
b1100000 A
b1100000 >
b1000 W
b1011100 B
b1011100 @
b1100001100010001100011 S
b1011000 D
b0 P
b0 =
b0 .
b0 d
b0 U
07
b0 3
b1100001001010001100011 O
b1010100 <
b1 ]
b1010100 *
b1000 T
1!
#250000
0!
#255000
1%
0Z
b0 \
0c
b11 6
1:
b0 0
b1100000 X
b1100000 ;
b1 N
b1 e
b0 W
b100001001101010001100011 Q
b1100000 A
b1100100 >
b0 O
b0 *
b0 <
b0 ]
b0 T
1Y
1b
b1000 [
b1100001100010001100011 R
b1011100 ?
b11000000000010 ^
b11000000000010 /
b1000 V
b0 a
b1011000 C
b1100000 @
b110110111 S
b1011100 D
b1100000 B
1!
#260000
0!
#265000
b0 6
0:
0%
b0 N
b0 e
b1100100 A
b0 X
b0 ;
b0 @
b0 S
b0 D
0Y
0b
b0 [
b0 R
b0 ?
b0 ^
b0 /
b0 V
b0 C
b1100001100010001100011 P
b1011100 =
b11000000000010 .
b1 d
b1000 U
1!
#270000
0!
#275000
b1100 \
1Z
1c
b111 0
b1000 2
b1000 W
b1000110111 Q
b1101000 A
b1101000 >
b1100001100010001100011 O
b1011100 *
b1011100 <
b1 ]
b1000 T
b0 P
b0 =
b0 .
b0 d
b0 U
b1100100 @
b100001001101010001100011 S
b1100000 D
b1100100 B
1!
#280000
0!
#285000
1%
0Z
b0 \
0c
b11 6
1:
b0 0
b0 2
b10100100110010001100011 Q
b1101000 A
b1101100 >
b0 W
b1101000 X
b1101000 ;
b1 N
b1 e
b1101000 B
b1101000 @
b1000110111 S
b1100100 D
1Y
1b
b1100 [
b100001001101010001100011 R
b1100100 ?
b111 ^
b111 /
b1000 1
b1000 V
b1000 a
b1100000 C
b0 O
b0 *
b0 <
b0 ]
b0 T
1!
#290000
0!
#295000
0%
b0 6
0:
b0 N
b0 e
b1101100 A
b0 X
b0 ;
b100001001101010001100011 P
b1100100 =
b111 .
b1 d
b1000 U
0Y
0b
b0 [
b0 R
b0 ?
b0 ^
b0 /
b0 a
b0 1
b0 V
b0 C
b0 @
b0 S
b0 D
1!
#300000
0!
#305000
b1001 \
1Z
1c
b101000000000100 0
b100000000000011 2
b1010110111 Q
b1110000 A
b1110000 >
b1000 W
b1101100 B
b1101100 @
b10100100110010001100011 S
b1101000 D
b0 P
b0 =
b0 .
b0 d
b0 U
b100001001101010001100011 O
b1100100 *
b1100100 <
b1 ]
b1000 T
1!
#310000
0!
#315000
1%
0Z
b0 \
0c
b11 6
1:
b0 0
b0 2
b1110000 X
b1110000 ;
b1 N
b1 e
b0 W
b100001000111010001100011 Q
b1110000 A
b1110100 >
b0 O
b0 *
b0 <
b0 ]
b0 T
1Y
1b
b1001 [
b10100100110010001100011 R
b1101100 ?
b101000000000100 ^
b101000000000100 /
b100000000000011 1
b1000 V
b100000000000011 a
b1101000 C
b1110000 @
b1010110111 S
b1101100 D
b1110000 B
1!
#320000
0!
#325000
b0 6
0:
0%
b0 N
b0 e
b1110100 A
b0 X
b0 ;
b0 @
b0 S
b0 D
0Y
0b
b0 [
b0 R
b0 ?
b0 ^
b0 /
b0 a
b0 1
b0 V
b0 C
b10100100110010001100011 P
b1101100 =
b101000000000100 .
b1 d
b1000 U
1!
#330000
0!
#335000
b1101 \
1Z
1c
b111 0
b111 2
b1000 W
b1100110111 Q
b1111000 A
b1111000 >
b10100100110010001100011 O
b1101100 *
b1101100 <
b1 ]
b1000 T
b0 P
b0 =
b0 .
b0 d
b0 U
b1110100 @
b100001000111010001100011 S
b1110000 D
b1110100 B
1!
#340000
0!
#345000
1%
0Z
b0 \
0c
b11 6
1:
b0 0
b0 2
bx Q
b1111000 A
b1111100 >
b0 W
b1111000 X
b1111000 ;
b1 N
b1 e
b1111000 B
b1111000 @
b1100110111 S
b1110100 D
1Y
1b
b1101 [
b100001000111010001100011 R
b1110100 ?
b111 ^
b111 /
b111 1
b1000 V
b111 a
b1110000 C
b0 O
b0 *
b0 <
b0 ]
b0 T
1!
#350000
0!
#355000
0%
b0 6
0:
b0 N
b0 e
b1111100 A
b0 X
b0 ;
b100001000111010001100011 P
b1110100 =
b111 .
b1 d
b1000 U
0Y
0b
b0 [
b0 R
b0 ?
b0 ^
b0 /
b0 a
b0 1
b0 V
b0 C
b0 @
b0 S
b0 D
1!
#360000
0!
#365000
bx 0
bx 2
b10000000 A
b10000000 >
b1111100 B
b1111100 @
bx S
b1111000 D
b0 P
b0 =
b0 .
b0 d
b0 U
b100001000111010001100011 O
b1110100 *
b1110100 <
b1 ]
b1000 T
1!
#370000
0!
#375000
b1111000 X
b1111000 ;
bx N
bx e
b10000100 A
b10000100 >
b0 O
b0 *
b0 <
b0 ]
b0 T
bx R
b1111100 ?
bx ^
bx /
bx 1
b1111000 a
b1111000 C
b10000000 @
b1111100 D
b10000000 B
1!
#380000
0!
#385000
b10001000 A
b10001000 >
b1111100 X
b1111100 ;
b10000100 B
b10000100 @
b10000000 D
b10000000 ?
b1111100 a
b1111100 C
bx P
b1111100 =
bx .
bx d
1!
#390000
0!
#395000
b10000000 X
b10000000 ;
b10001100 A
b10001100 >
bx O
b1111100 *
b1111100 <
bx ]
b10000000 =
b10000100 ?
b10000000 a
b10000000 C
b10001000 @
b10000100 D
b10001000 B
1!
#400000
0!
#405000
b10010000 A
b10010000 >
b10000100 X
b10000100 ;
b10001100 B
b10001100 @
b10001000 D
b10001000 ?
b10000100 a
b10000100 C
b10000100 =
b10000000 *
b10000000 <
1!
#410000
0!
#415000
b10001000 X
b10001000 ;
b10010100 A
b10010100 >
b10000100 *
b10000100 <
b10001000 =
b10001100 ?
b10001000 a
b10001000 C
b10010000 @
b10001100 D
b10010000 B
1!
#420000
0!
#425000
b10011000 A
b10011000 >
b10001100 X
b10001100 ;
b10010100 B
b10010100 @
b10010000 D
b10010000 ?
b10001100 a
b10001100 C
b10001100 =
b10001000 *
b10001000 <
1!
#430000
0!
#435000
b10010000 X
b10010000 ;
b10011100 A
b10011100 >
b10001100 *
b10001100 <
b10010000 =
b10010100 ?
b10010000 a
b10010000 C
b10011000 @
b10010100 D
b10011000 B
1!
#440000
0!
#445000
b10100000 A
b10100000 >
b10010100 X
b10010100 ;
b10011100 B
b10011100 @
b10011000 D
b10011000 ?
b10010100 a
b10010100 C
b10010100 =
b10010000 *
b10010000 <
1!
#450000
0!
#455000
b10011000 X
b10011000 ;
b10100100 A
b10100100 >
b10010100 *
b10010100 <
b10011000 =
b10011100 ?
b10011000 a
b10011000 C
b10100000 @
b10011100 D
b10100000 B
1!
#460000
0!
#465000
b10101000 A
b10101000 >
b10011100 X
b10011100 ;
b10100100 B
b10100100 @
b10100000 D
b10100000 ?
b10011100 a
b10011100 C
b10011100 =
b10011000 *
b10011000 <
1!
#470000
0!
#475000
b10100000 X
b10100000 ;
b10101100 A
b10101100 >
b10011100 *
b10011100 <
b10100000 =
b10100100 ?
b10100000 a
b10100000 C
b10101000 @
b10100100 D
b10101000 B
1!
#480000
0!
