src/RegisterFile.v

module register_file(
    input clk, 
    input we,
    input [4:0] raddr1, //address to read from
    input [4:0] raddr2, //32 registers so 5 bits
    input [4:0] waddr, //address to write to
    input [31:0] wdata, //data to write
    output [31:0] rdata1, //data read
    output [31:0] rdata2
);

    //32 registers
    //not really gonna use the first one, but complicates to remove it
    reg [31:0] register [31:0];

    //read
    //async for single cycle reasons
    //turnary operator is used since we don't know the initial state of register[0]
    assign rdata1 = (raddr1 == 5'd0) ? 32'd0 : register[raddr1];
    assign rdata2 = (raddr2 == 5'd0) ? 32'd0 : register[raddr2];

    //write
    always @(posedge clk) begin
        if(we && (waddr != 5'd0))
            register[waddr] <= wdata;
    end

endmodule

src/ImmediateGenerator.v
module immediate_generator (
    input [31:0] data_in,
    output reg [31:0] data_out
);

always @(*) begin
    data_out = 32'd0;
    case(data_in[6:0])
        //I-type
        7'b0010011, 7'b0000011, 7'b1100111: begin
            data_out = {{21{data_in[31]}}, data_in[30:20]};
        end
        //S-Type
        7'b0100011: begin
            data_out = {{21{data_in[31]}}, data_in[30:25], data_in[11:7]};
        end
        //B-Type
        7'b1100011: begin
            data_out = {{20{data_in[31]}}, data_in[7], data_in[30:25], data_in[11:8], 1'b0};
        end
        //U-Type
        7'b0110111, 7'b0010111: begin
            data_out = {data_in[31:12], 12'd0};
        end
        //J-Type
        7'b1101111: begin
            data_out = {{12{data_in[31]}}, data_in[19:12], data_in[20], data_in[30:21], 1'b0};
        end

        default: data_out = 32'd0;
    endcase
end


endmodule

src/IF_ID.v
module if_id (
    input clk,
    input FLUSH_E,
    input reset,
    input [31:0] PCF,
    input [31:0] InstrF,
    input [31:0] PCPlus4F,
    output reg [31:0] PCD,
    output reg [31:0] InstrD,
    output reg [31:0] PCPlus4D
);

    always @(posedge clk) begin
        if(reset | FLUSH_E) begin
            PCD <= 32'd0;
            InstrD <= 32'd0;
            PCPlus4D <= 32'd0;
        end
        else begin
            PCD <= PCF;
            InstrD <= InstrF;
            PCPlus4D <= PCPlus4F;
        end

    end

endmodule

src/MUX.v
module mux #(
    parameter DATA_WIDTH = 32,
    parameter INPUT_WIDTH = 2,
    parameter SELECT_BITS = 1
) (
    input [(INPUT_WIDTH*DATA_WIDTH)-1:0] data_in,
    input [SELECT_BITS-1:0] sel,
    output [DATA_WIDTH-1:0] out
);

    assign out = data_in[sel*(DATA_WIDTH) +: DATA_WIDTH];

endmodule

src/ALU.v
module alu (
    input [31:0] a,
    input [31:0] b,
    input [3:0] sel,
    output reg [31:0] s,
    output zero
    );

    assign zero = (s == 32'd0);

    always @(*) begin
        case(sel)
            4'd0: s = a + b; //add
            4'd1: s = a - b; //sub
            4'd2: s = a ^ b; //xor
            4'd3: s = a | b; //or
            4'd4: s = a & b; //and
            4'd5: s = a << b[4:0]; //sll
            4'd6: s = a >> b[4:0]; //srl
            4'd7: s = $signed(a) >>> b[4:0]; //sra
            4'd8: s = ($signed(a) < $signed(b)) ? 1 : 0; //slt
            4'd9: s = ($unsigned(a) < $unsigned(b)) ? 1 : 0; //sltu
            4'd10: s = (a == b) ? 1 : 0; //beq
            4'd11: s = (a != b) ? 1 : 0; //bne
            4'd12: s = ($signed(a) >= $signed(b)) ? 1 : 0; //bge
            4'd13: s = ($unsigned(a) >= $unsigned(b)) ? 1 : 0; //bgeu
            4'd14: s = 32'd1; //For unconditional jumpsS 
            default: s = 32'd0;
        endcase
    end
endmodule

src/InstructionMemory.v
module instruction_memory (
    input  [31:0] raddr,
    output [31:0] instr
);

    // Smaller size for simulation
    reg [7:0] instruction_memory [0:1023];

    // Load program
    initial begin
        $readmemh("prog/nh_pipelined_test_jump.hex", instruction_memory, 8'd0);
    end

    //using 32-bit word size, but using the higher bits of pc
    assign instr = {instruction_memory[raddr[9:0]], instruction_memory[raddr[9:0]+1], instruction_memory[raddr[9:0]+2], instruction_memory[raddr[7:0]+3]};

endmodule

src/ProgramCounter.v
module program_counter (
    input clk,
    input reset,
    input [31:0] wdata,
    output [31:0] rdata
);
    reg [31:0] program_counter;

    assign rdata = program_counter;

    always @(posedge clk) begin
        if(reset)
            program_counter = 32'd0;
        else
            program_counter <= wdata;
    end

endmodule

src/Pipelined_CPU.v
module p_cpu (input clk, input reset);

    // ==================== WIRES ====================

    // INSTRUCION FETCH
    wire [31:0] PCMUX_OUT, PCF, WIRED4_F, InstrF, PCPlus4F;

    // INSTRUCTION DECODE
    wire [31:0] PCD, InstrD, PCPlus4D, ImmD, RS1D, RS2D;
    wire [1:0] REG_MUX_D;
    wire REG_EN_D;
    wire WE_D;
    wire SZ_D;
    wire [1:0] NUM_BYTES_D;
    wire JUMP_D;
    wire JALR_D;
    wire [3:0] ALU_SEL_D;
    wire ALUMUX1_D;
    wire ALUMUX2_D;
    wire BR_EN_D;

    // EXECUTE
    wire [31:0] PCE, ImmE, RS1E, RS2E, PCPlus4E, PCPlusImmE, ALUE, ALUMUX1_OUT, ALUMUX2_OUT, JALRMUX_OUT, CTAddrE, InstrE;
    wire FLUSH_E;
    wire [1:0] REG_MUX_E;
    wire REG_EN_E;
    wire WE_E;
    wire SZ_E;
    wire [1:0] NUM_BYTES_E;
    wire JUMP_E;
    wire JALR_E;
    wire [3:0] ALU_SEL_E;
    wire ALUMUX1_E;
    wire ALUMUX2_E;
    wire BR_EN_E;

    // MEMORY
    wire [31:0] ImmM, ALUM, RS2M, PCPlus4M, MEMM, InstrM;
    wire [1:0] REG_MUX_M;
    wire REG_EN_M;
    wire WE_M;
    wire SZ_M;
    wire [1:0] NUM_BYTES_M;

    // WRITEBACK
    wire [31:0] ImmW, ALUW, MEMW, PCPlus4W, WBDataW, InstrW;
    wire [1:0] REG_MUX_W; 
    wire REG_EN_W;

    assign WIRED4_F = 32'd4;

    //pUT THIS INTO EXECUTE
    assign FLUSH_E = JUMP_E | (BR_EN_E & ALUE[0]);

    // ==================== MODULES ====================

    // iNSTRUCTION FETCH
    program_counter program_counter (
        .clk(clk),
        .reset(reset),
        .wdata(PCMUX_OUT),
        .rdata(PCF)
    );

    instruction_memory instruction_memory (
        .raddr(PCF),
        .instr(InstrF)
    );

    alu pc_plus_4 (
        .a(PCF),
        .b(WIRED4_F),
        .sel(4'd0),
        .s(PCPlus4F)
    );

    mux #(.DATA_WIDTH(32), .INPUT_WIDTH(2), .SELECT_BITS(1)) pcmux (
        .data_in({CTAddrE, PCPlus4F}),
        .sel(FLUSH_E),
        .out(PCMUX_OUT)
    );

    // IF/ID REGISTER

    if_id if_id (
        .clk(clk),
        .FLUSH_E(FLUSH_E),
        .reset(reset),
        .PCF(PCF),
        .InstrF(InstrF),
        .PCPlus4F(PCPlus4F),
        .PCD(PCD),
        .InstrD(InstrD),
        .PCPlus4D(PCPlus4D)
    );

    // INSTRUCTION DECODE

    immediate_generator immediate_generator (
        .data_in(InstrD),
        .data_out(ImmD)
    );

    register_file register_file(
        .clk(clk),
        .we(REG_EN_W),
        .raddr1(InstrD[19:15]),
        .raddr2(InstrD[24:20]),
        .waddr(InstrW[11:7]),
        .wdata(WBDataW),
        .rdata1(RS1D),
        .raddr2(RS2D)
    );




endmodule

tb/TB_Pipelined_CPU_NH/NH_Jump.v
`timescale 1ns/1ps

module NH_Jump;

    reg clk;
    reg reset;

    reg [31:0] expected [0:31];
    integer i;
    integer errors;

    initial begin
        expected[0] = 32'h00000000;
        expected[1] = 32'h0000000C;
        expected[2] = 32'h00000028;
    end

    p_cpu test_cpu (.clk(clk), .reset(reset));

    always #5 clk = ~clk;

    initial begin
        clk = 1'b0;

        $dumpfile("sim/nh_jump.vcd");
        $dumpvars(1, NH_Jump, NH_Jump.test_cpu);

        reset = 1'b1;

        @(posedge clk); #1;

        reset = 1'b0;

        repeat(50) @(posedge clk);

        errors = 0;

        for (i = 0; i < 3; i = i + 1) begin
            if (test_cpu.register_file.register[i] !== expected[i]) begin
                errors = errors + 1;
                $display("FAIL AT R%0d: expected %08h, got %08h",
                        i,
                        expected[i],
                        test_cpu.register_file.register[i]);
            end
        end

        if (errors == 0)
            $display("PASS: Pipelined Jump test");
        else
            $display("FAIL: %0d register mismatches", errors);

        $finish;

    end

endmodule

sim/nh_jump.vcd
$date
	Fri Jun 19 03:09:32 2026
$end
$version
	Icarus Verilog
$end
$timescale
	1ps
$end
$scope module NH_Jump $end
$var reg 1 ! clk $end
$var reg 1 " reset $end
$var integer 32 # errors [31:0] $end
$var integer 32 $ i [31:0] $end
$upscope $end
$scope module NH_Jump $end
$scope module test_cpu $end
$var wire 1 % FLUSH_E $end
$var wire 32 & WIRED4_F [31:0] $end
$var wire 1 ! clk $end
$var wire 1 " reset $end
$var wire 1 ' WE_M $end
$var wire 1 ( WE_E $end
$var wire 1 ) WE_D $end
$var wire 32 * WBDataW [31:0] $end
$var wire 1 + SZ_M $end
$var wire 1 , SZ_E $end
$var wire 1 - SZ_D $end
$var wire 32 . RS2M [31:0] $end
$var wire 32 / RS2E [31:0] $end
$var wire 32 0 RS2D [31:0] $end
$var wire 32 1 RS1E [31:0] $end
$var wire 32 2 RS1D [31:0] $end
$var wire 2 3 REG_MUX_W [1:0] $end
$var wire 2 4 REG_MUX_M [1:0] $end
$var wire 2 5 REG_MUX_E [1:0] $end
$var wire 2 6 REG_MUX_D [1:0] $end
$var wire 1 7 REG_EN_W $end
$var wire 1 8 REG_EN_M $end
$var wire 1 9 REG_EN_E $end
$var wire 1 : REG_EN_D $end
$var wire 32 ; PCPlusImmE [31:0] $end
$var wire 32 < PCPlus4W [31:0] $end
$var wire 32 = PCPlus4M [31:0] $end
$var wire 32 > PCPlus4F [31:0] $end
$var wire 32 ? PCPlus4E [31:0] $end
$var wire 32 @ PCPlus4D [31:0] $end
$var wire 32 A PCMUX_OUT [31:0] $end
$var wire 32 B PCF [31:0] $end
$var wire 32 C PCE [31:0] $end
$var wire 32 D PCD [31:0] $end
$var wire 2 E NUM_BYTES_M [1:0] $end
$var wire 2 F NUM_BYTES_E [1:0] $end
$var wire 2 G NUM_BYTES_D [1:0] $end
$var wire 32 H MEMW [31:0] $end
$var wire 32 I MEMM [31:0] $end
$var wire 1 J JUMP_E $end
$var wire 1 K JUMP_D $end
$var wire 1 L JALR_E $end
$var wire 1 M JALR_D $end
$var wire 32 N JALRMUX_OUT [31:0] $end
$var wire 32 O InstrW [31:0] $end
$var wire 32 P InstrM [31:0] $end
$var wire 32 Q InstrF [31:0] $end
$var wire 32 R InstrE [31:0] $end
$var wire 32 S InstrD [31:0] $end
$var wire 32 T ImmW [31:0] $end
$var wire 32 U ImmM [31:0] $end
$var wire 32 V ImmE [31:0] $end
$var wire 32 W ImmD [31:0] $end
$var wire 32 X CTAddrE [31:0] $end
$var wire 1 Y BR_EN_E $end
$var wire 1 Z BR_EN_D $end
$var wire 4 [ ALU_SEL_E [3:0] $end
$var wire 4 \ ALU_SEL_D [3:0] $end
$var wire 32 ] ALUW [31:0] $end
$var wire 32 ^ ALUMUX2_OUT [31:0] $end
$var wire 1 _ ALUMUX2_E $end
$var wire 1 ` ALUMUX2_D $end
$var wire 32 a ALUMUX1_OUT [31:0] $end
$var wire 1 b ALUMUX1_E $end
$var wire 1 c ALUMUX1_D $end
$var wire 32 d ALUM [31:0] $end
$var wire 32 e ALUE [31:0] $end
$upscope $end
$upscope $end
$enddefinitions $end
$comment Show the parameter values. $end
$dumpall
$end
#0
$dumpvars
bx e
bx d
xc
xb
bx a
x`
x_
bx ^
bx ]
bx \
bx [
xZ
xY
bx X
bx W
bx V
bx U
bx T
bx S
bx R
bx Q
bx P
bx O
bx N
xM
xL
xK
xJ
bx I
bx H
bx G
bx F
bx E
bx D
bx C
bx B
bx A
bx @
bx ?
bx >
bx =
bx <
bx ;
x:
x9
x8
x7
bx 6
bx 5
bx 4
bx 3
bx 2
bx 1
bx 0
bx /
bx .
x-
x,
x+
bx *
x)
x(
x'
b100 &
x%
bx $
bx #
1"
0!
$end
#5000
b0 G
0-
0)
0M
0Z
0K
b0 \
0`
0c
b0 6
0:
b0 0
b0 2
b100 A
0%
b0 W
b0 N
b0 e
b0 X
b0 ;
b0xxxxxxxx I
b0 @
b0 S
b0 D
0Y
b0 ^
0_
b0 a
0b
b0 [
0L
0J
b0 F
0,
0(
09
b0 5
b0 R
b0 ?
b0 /
b0 1
b0 V
b0 C
b0 E
0+
0'
08
b0 4
b0 P
b0 =
b0 .
b0 d
b0 U
07
b0 *
b0 3
b0 O
b0 <
b0 H
b0 ]
b0 T
b10110111 Q
b100 >
b0 B
1!
#6000
0"
#10000
0!
#15000
b11 6
1:
b100110111 Q
b1000 A
b1000 >
b0xxxxxxxx H
b100 @
b10110111 S
b100 B
1!
#20000
0!
#25000
b100000000000000011101111 Q
b1100 A
b1100 >
b1000 B
b1000 @
b100110111 S
b100 D
19
b11 5
b10110111 R
b100 ?
1!
#30000
0!
#35000
1K
1`
b0 6
bx 0
b100 X
b100 ;
b100 N
b100 e
b1000 W
b1000010110111 Q
b10000 A
b10000 >
18
b11 4
b10110111 P
b100 =
b100110111 R
b1000 ?
b100 a
b100 C
b1100 @
b100000000000000011101111 S
b1000 D
b1100 B
1!
#40000
0!
#45000
0K
0`
b11 6
b0 0
b10011 Q
b10100 >
b1000000000000 W
1%
b10000 ;
b10000 X
b10000 N
b10000 e
b10000 B
b10000 @
b1000010110111 S
b1100 D
1_
1J
b0 5
b100000000000000011101111 R
b1100 ?
b1000 ^
bx /
b1000 V
b1000 a
b1000 C
b100110111 P
b1000 =
b100 d
17
b11 3
b10110111 O
b0 *
b100 <
1!
#50000
0!
#55000
b0 6
0:
0%
b10100 A
b0 X
b0 ;
b0 N
b0 e
b0 W
b100110111 O
b1000 <
b100 ]
b0 4
b100000000000000011101111 P
b1100 =
bx .
b10000 d
b1000 U
0_
0J
09
b0 R
b0 ?
b0 /
b0 ^
b0 V
b0 a
b0 C
b0 @
b0 S
b0 D
1!
#60000
0!
#65000
1`
1c
b1 6
1:
b11000 A
b11000 >
b10100 B
b10100 @
b10011 S
b10000 D
08
b0 P
b0 =
b0 .
b0 d
b0 U
b0 3
b100000000000000011101111 O
b1100 <
b10000 ]
b1100 *
b1000 T
1!
#70000
0!
#75000
b10000 X
b10000 ;
b11100 A
b11100 >
07
b0 O
b0 *
b0 <
b0 ]
b0 T
1_
1b
19
b1 5
b10011 R
b10100 ?
b0 a
b10000 C
b11000 @
b10100 D
b11000 B
1!
#80000
0!
#85000
b100000 A
b100000 >
b10100 X
b10100 ;
b11100 B
b11100 @
b11000 D
b11000 ?
b10100 C
18
b1 4
b10011 P
b10100 =
1!
#90000
0!
#95000
b11000 X
b11000 ;
b100100 A
b100100 >
17
b1 3
b10011 O
b0 *
b10100 <
b11000 =
b11100 ?
b11000 C
b100000 @
b11100 D
b100000 B
1!
#100000
0!
#105000
b10000000000010000000101100111 Q
b101000 A
b101000 >
b11100 X
b11100 ;
b100100 B
b100100 @
b100000 D
b100000 ?
b11100 C
b11100 =
b11000 <
1!
#110000
0!
#115000
1M
1K
b0 6
b100000 X
b100000 ;
b100000000 W
b1000100110111 Q
b101100 A
b101100 >
b11100 <
b100000 =
b100100 ?
b100000 C
b101000 @
b10000000000010000000101100111 S
b100100 D
b101000 B
1!
#120000
0!
#125000
0M
0K
0`
0c
b11 6
b100000000 N
bx Q
b110000 >
b1000000000000 W
b100000000 A
1%
b100000000 e
b100100100 ;
b101100 B
b101100 @
b1000100110111 S
b101000 D
1L
b100000000 X
1J
b0 5
b10000000000010000000101100111 R
b101000 ?
b100000000 ^
b100000000 V
b100100 C
b100100 =
b100000 <
1!
#130000
0!
#135000
b0 6
0:
0%
b0 N
b0 e
b0 ;
b0 W
bx10110111 Q
b100000100 >
b100100 <
b0 4
b10000000000010000000101100111 P
b101000 =
b100000000 d
b100000000 U
0_
0b
0L
b100000100 A
b0 X
0J
09
b0 R
b0 ?
b0 ^
b0 V
b0 C
b0 @
b0 S
b0 D
b100000000 B
1!
#140000
0!
#145000
b11 6
1:
bx 0
bx 2
bx00110111 Q
b100001000 A
b100001000 >
bx000000000000 W
b100000100 B
b100000100 @
bx10110111 S
b100000000 D
08
b0 P
b0 =
b0 d
b0 U
b0 3
b10000000000010000000101100111 O
b101000 <
b101000 *
b100000000 ]
b100000000 T
1!
#150000
0!
#155000
bx X
bx ;
bx N
bx e
bx000000000000 W
bx11101111 Q
b100001100 A
b100001100 >
07
b0 O
b0 *
b0 <
b0 ]
b0 T
19
b11 5
bx10110111 R
b100000100 ?
bx ^
bx /
bx 1
bx000000000000 V
b100000000 a
b100000000 C
b100001000 @
bx00110111 S
b100000100 D
b100001000 B
1!
#160000
0!
#165000
1K
1`
b0 6
bx10110111 Q
b100010000 A
b100010000 >
bx0 W
b100001100 B
b100001100 @
bx11101111 S
b100001000 D
bx00110111 R
b100001000 ?
b100000100 a
b100000100 C
18
b11 4
bx10110111 P
b100000100 =
bx .
bx d
bx000000000000 U
1!
#170000
0!
#175000
0K
0`
b11 6
1%
bx000000000000 W
bx00010011 Q
bx A
b100010100 >
17
b11 3
bx10110111 O
bx000000000000 *
b100000100 <
bx ]
bx000000000000 T
bx00110111 P
b100001000 =
bx0 ^
1_
1J
b0 5
bx11101111 R
b100001100 ?
bx0 V
b100001000 a
b100001000 C
b100010000 @
bx10110111 S
b100001100 D
b100010000 B
1!
#180000
0!
#185000
b0 6
0:
b0 0
b0 2
bx Q
bx >
b0 W
0%
bx A
b0 X
b0 ;
b0 N
b0 e
bx B
b0 @
b0 S
b0 D
0_
0J
09
b0 R
b0 ?
b0 /
b0 1
b0 ^
b0 V
b0 a
b0 C
b0 4
bx11101111 P
b100001100 =
bx0 U
bx00110111 O
b100001000 <
1!
#190000
0!
#195000
bx 0
bx 2
b0 3
bx11101111 O
b100001100 <
b100001100 *
bx0 T
08
b0 P
b0 =
b0 .
b0 d
b0 U
bx @
bx S
bx D
1!
#200000
0!
#205000
bx X
bx ;
bx N
bx e
bx R
bx ?
bx ^
bx /
bx 1
bx a
bx C
07
b0 O
b0 *
b0 <
b0 ]
b0 T
1!
#210000
0!
#215000
bx P
bx =
bx .
bx d
1!
#220000
0!
#225000
bx O
bx *
bx <
bx ]
1!
