src/RegisterFile.v

module register_file(
    input clk, 
    input we,
    input [4:0] raddr1, //address to read from
    input [4:0] raddr2, //32 registers so 5 bits
    input [4:0] waddr, //address to write to
    input [31:0] wdata, //data to write
    output [31:0] rdata1, //data read
    output [31:0] rdata2
);

    //32 registers
    //not really gonna use the first one, but complicates to remove it
    reg [31:0] register [31:0];

    //read
    //async for single cycle reasons
    //turnary operator is used since we don't know the initial state of register[0]
    assign rdata1 = (raddr1 == 5'd0) ? 32'd0 : register[raddr1];
    assign rdata2 = (raddr2 == 5'd0) ? 32'd0 : register[raddr2];

    //write
    always @(posedge clk) begin
        if(we && (waddr != 5'd0))
            register[waddr] <= wdata;
    end

endmodule

src/ImmediateGenerator.v
module immediate_generator (
    input [31:0] data_in,
    output reg [31:0] data_out
);

always @(*) begin
    data_out = 32'd0;
    case(data_in[6:0])
        //I-type
        7'b0010011, 7'b0000011, 7'b1100111: begin
            data_out = {{21{data_in[31]}}, data_in[30:20]};
        end
        //S-Type
        7'b0100011: begin
            data_out = {{21{data_in[31]}}, data_in[30:25], data_in[11:7]};
        end
        //B-Type
        7'b1100011: begin
            data_out = {{20{data_in[31]}}, data_in[7], data_in[30:25], data_in[11:8], 1'b0};
        end
        //U-Type
        7'b0110111, 7'b0010111: begin
            data_out = {data_in[31:12], 12'd0};
        end
        //J-Type
        7'b1101111: begin
            data_out = {{12{data_in[31]}}, data_in[19:12], data_in[20], data_in[30:21], 1'b0};
        end

        default: data_out = 32'd0;
    endcase
end


endmodule

src/IF_ID.v
module if_id (
    input clk,
    input FLUSH_E,
    input reset,
    input [31:0] PCF,
    input [31:0] InstrF,
    input [31:0] PCPlus4F,
    output reg [31:0] PCD,
    output reg [31:0] InstrD,
    output reg [31:0] PCPlus4D
);

    always @(posedge clk) begin
        if(reset | FLUSH_E) begin
            PCD <= 32'd0;
            InstrD <= 32'd0;
            PCPlus4D <= 32'd0;
        end
        else begin
            PCD <= PCF;
            InstrD <= InstrF;
            PCPlus4D <= PCPlus4F;
        end

    end

endmodule

src/MUX.v
module mux #(
    parameter DATA_WIDTH = 32,
    parameter INPUT_WIDTH = 2,
    parameter SELECT_BITS = 1
) (
    input [(INPUT_WIDTH*DATA_WIDTH)-1:0] data_in,
    input [SELECT_BITS-1:0] sel,
    output [DATA_WIDTH-1:0] out
);

    assign out = data_in[sel*(DATA_WIDTH) +: DATA_WIDTH];

endmodule

src/ALU.v
module alu (
    input [31:0] a,
    input [31:0] b,
    input [3:0] sel,
    output reg [31:0] s,
    output zero
    );

    assign zero = (s == 32'd0);

    always @(*) begin
        case(sel)
            4'd0: s = a + b; //add
            4'd1: s = a - b; //sub
            4'd2: s = a ^ b; //xor
            4'd3: s = a | b; //or
            4'd4: s = a & b; //and
            4'd5: s = a << b[4:0]; //sll
            4'd6: s = a >> b[4:0]; //srl
            4'd7: s = $signed(a) >>> b[4:0]; //sra
            4'd8: s = ($signed(a) < $signed(b)) ? 1 : 0; //slt
            4'd9: s = ($unsigned(a) < $unsigned(b)) ? 1 : 0; //sltu
            4'd10: s = (a == b) ? 1 : 0; //beq
            4'd11: s = (a != b) ? 1 : 0; //bne
            4'd12: s = ($signed(a) >= $signed(b)) ? 1 : 0; //bge
            4'd13: s = ($unsigned(a) >= $unsigned(b)) ? 1 : 0; //bgeu
            4'd14: s = 32'd1; //For unconditional jumpsS 
            default: s = 32'd0;
        endcase
    end
endmodule

src/InstructionMemory.v
module instruction_memory (
    input  [31:0] raddr,
    output [31:0] instr
);

    // Smaller size for simulation
    reg [7:0] instruction_memory [0:1023];

    // Load program
    initial begin
        $readmemh("prog/nh_pipelined_test_reg_op.hex", instruction_memory, 8'd0);
    end

    //using 32-bit word size, but using the higher bits of pc
    assign instr = {instruction_memory[raddr[9:0]], instruction_memory[raddr[9:0]+1], instruction_memory[raddr[9:0]+2], instruction_memory[raddr[7:0]+3]};

endmodule

src/ProgramCounter.v
module program_counter (
    input clk,
    input reset,
    input [31:0] wdata,
    output [31:0] rdata
);
    reg [31:0] program_counter;

    assign rdata = program_counter;

    always @(posedge clk) begin
        if(reset)
            program_counter = 32'd0;
        else
            program_counter <= wdata;
    end

endmodule

src/Pipelined_CPU.v
module p_cpu (input clk, input reset);

    // ==================== WIRES ====================

    // INSTRUCION FETCH
    wire [31:0] PCMUX_OUT, PCF, WIRED4_F, InstrF, PCPlus4F;

    // INSTRUCTION DECODE
    wire [31:0] PCD, InstrD, PCPlus4D, ImmD, RS1D, RS2D;
    wire [1:0] REG_MUX_D;
    wire REG_EN_D;
    wire WE_D;
    wire SZ_D;
    wire [1:0] NUM_BYTES_D;
    wire JUMP_D;
    wire JALR_D;
    wire [3:0] ALU_SEL_D;
    wire ALUMUX1_D;
    wire ALUMUX2_D;
    wire BR_EN_D;

    // EXECUTE
    wire [31:0] PCE, ImmE, RS1E, RS2E, PCPlus4E, PCPlusImmE, ALUE, ALUMUX1_OUT, ALUMUX2_OUT, JALRMUX_OUT, CTAddrE, InstrE;
    wire FLUSH_E;
    wire [1:0] REG_MUX_E;
    wire REG_EN_E;
    wire WE_E;
    wire SZ_E;
    wire [1:0] NUM_BYTES_E;
    wire JUMP_E;
    wire JALR_E;
    wire [3:0] ALU_SEL_E;
    wire ALUMUX1_E;
    wire ALUMUX2_E;
    wire BR_EN_E;

    // MEMORY
    wire [31:0] ImmM, ALUM, RS2M, PCPlus4M, MEMM, InstrM;
    wire [1:0] REG_MUX_M;
    wire REG_EN_M;
    wire WE_M;
    wire SZ_M;
    wire [1:0] NUM_BYTES_M;

    // WRITEBACK
    wire [31:0] ImmW, ALUW, MEMW, PCPlus4W, WBDataW, InstrW;
    wire [1:0] REG_MUX_W; 
    wire REG_EN_W;

    assign WIRED4_F = 32'd4;

    //pUT THIS INTO EXECUTE
    assign FLUSH_E = JUMP_E | (BR_EN_E & ALUE[0]);

    // ==================== MODULES ====================

    // iNSTRUCTION FETCH
    program_counter program_counter (
        .clk(clk),
        .reset(reset),
        .wdata(PCMUX_OUT),
        .rdata(PCF)
    );

    instruction_memory instruction_memory (
        .raddr(PCF),
        .instr(InstrF)
    );

    alu pc_plus_4 (
        .a(PCF),
        .b(WIRED4_F),
        .sel(4'd0),
        .s(PCPlus4F)
    );

    mux #(.DATA_WIDTH(32), .INPUT_WIDTH(2), .SELECT_BITS(1)) pcmux (
        .data_in({CTAddrE, PCPlus4F}),
        .sel(FLUSH_E),
        .out(PCMUX_OUT)
    );

    // IF/ID REGISTER

    if_id if_id (
        .clk(clk),
        .FLUSH_E(FLUSH_E),
        .reset(reset),
        .PCF(PCF),
        .InstrF(InstrF),
        .PCPlus4F(PCPlus4F),
        .PCD(PCD),
        .InstrD(InstrD),
        .PCPlus4D(PCPlus4D)
    );

    // INSTRUCTION DECODE

    immediate_generator immediate_generator (
        .data_in(InstrD),
        .data_out(ImmD)
    );

    register_file register_file(
        .clk(clk),
        .we(REG_EN_W),
        .raddr1(InstrD[19:15]),
        .raddr2(InstrD[24:20]),
        .waddr(InstrW[11:7]),
        .wdata(WBDataW),
        .rdata1(RS1D),
        .raddr2(RS2D)
    );




endmodule

tb/TB_Pipelined_CPU_NH/NH_RegOp.v
`timescale 1ns/1ps

module NH_RegOp;

    reg clk;
    reg reset;

    reg [31:0] expected [0:31];
    integer i;
    integer errors;

    initial begin
        expected[0]  = 32'h00000000;
        expected[1]  = 32'h00001001;
        expected[2]  = 32'h00002000;
        expected[3]  = 32'h00003000;
        expected[4]  = 32'h00004000;
        expected[5]  = 32'h00005000;
        expected[6]  = 32'h00006000;
        expected[7]  = 32'h00007000;
        expected[8]  = 32'h00008000;
        expected[9]  = 32'h00009000;

        expected[10] = 32'h00001001;
        expected[11] = 32'hFFFFEFFF;
        expected[12] = 32'h00001001;
        expected[14] = 32'h00009001;
        expected[15] = 32'h00001000;
        expected[16] = 32'h00004000;
        expected[17] = 32'h00001000;
        expected[18] = 32'h00001000;
        expected[19] = 32'h00000001;
        expected[20] = 32'h00000001;
    end

    p_cpu test_cpu (.clk(clk), .reset(reset));

    always #5 clk = ~clk;

    initial begin
        clk = 1'b0;

        $dumpfile("sim/nh_reg_op.vcd");
        $dumpvars(1, NH_RegOp.test_cpu, NH_RegOp);

        reset = 1'b1;

        @(posedge clk); #1;

        reset = 1'b0;

        repeat(50) @(posedge clk);

        errors = 0;

        for (i = 0; i < 21; i = i + 1) begin
            if (test_cpu.register_file.register[i] !== expected[i]) begin
                errors = errors + 1;
                $display("FAIL AT R%0d: expected %08h, got %08h",
                        i,
                        expected[i],
                        test_cpu.register_file.register[i]);
            end
        end

        if (errors == 0)
            $display("PASS: No Hazards Pipelined Register-Register Operations test");
        else
            $display("FAIL: %0d register mismatches", errors);

        $finish;

    end

endmodule

sim/nh_reg_op.vcd
$date
	Fri Jun 19 02:03:48 2026
$end
$version
	Icarus Verilog
$end
$timescale
	1ps
$end
$scope module NH_RegOp $end
$scope module test_cpu $end
$var wire 1 ! FLUSH_E $end
$var wire 32 " WIRED4_F [31:0] $end
$var wire 1 # clk $end
$var wire 1 $ reset $end
$var wire 1 % WE_M $end
$var wire 1 & WE_E $end
$var wire 1 ' WE_D $end
$var wire 32 ( WBDataW [31:0] $end
$var wire 1 ) SZ_M $end
$var wire 1 * SZ_E $end
$var wire 1 + SZ_D $end
$var wire 32 , RS2M [31:0] $end
$var wire 32 - RS2E [31:0] $end
$var wire 32 . RS2D [31:0] $end
$var wire 32 / RS1E [31:0] $end
$var wire 32 0 RS1D [31:0] $end
$var wire 2 1 REG_MUX_W [1:0] $end
$var wire 2 2 REG_MUX_M [1:0] $end
$var wire 2 3 REG_MUX_E [1:0] $end
$var wire 2 4 REG_MUX_D [1:0] $end
$var wire 1 5 REG_EN_W $end
$var wire 1 6 REG_EN_M $end
$var wire 1 7 REG_EN_E $end
$var wire 1 8 REG_EN_D $end
$var wire 32 9 PCPlusImmE [31:0] $end
$var wire 32 : PCPlus4W [31:0] $end
$var wire 32 ; PCPlus4M [31:0] $end
$var wire 32 < PCPlus4F [31:0] $end
$var wire 32 = PCPlus4E [31:0] $end
$var wire 32 > PCPlus4D [31:0] $end
$var wire 32 ? PCMUX_OUT [31:0] $end
$var wire 32 @ PCF [31:0] $end
$var wire 32 A PCE [31:0] $end
$var wire 32 B PCD [31:0] $end
$var wire 2 C NUM_BYTES_M [1:0] $end
$var wire 2 D NUM_BYTES_E [1:0] $end
$var wire 2 E NUM_BYTES_D [1:0] $end
$var wire 32 F MEMW [31:0] $end
$var wire 32 G MEMM [31:0] $end
$var wire 1 H JUMP_E $end
$var wire 1 I JUMP_D $end
$var wire 1 J JALR_E $end
$var wire 1 K JALR_D $end
$var wire 32 L JALRMUX_OUT [31:0] $end
$var wire 32 M InstrW [31:0] $end
$var wire 32 N InstrM [31:0] $end
$var wire 32 O InstrF [31:0] $end
$var wire 32 P InstrE [31:0] $end
$var wire 32 Q InstrD [31:0] $end
$var wire 32 R ImmW [31:0] $end
$var wire 32 S ImmM [31:0] $end
$var wire 32 T ImmE [31:0] $end
$var wire 32 U ImmD [31:0] $end
$var wire 32 V CTAddrE [31:0] $end
$var wire 1 W BR_EN_E $end
$var wire 1 X BR_EN_D $end
$var wire 4 Y ALU_SEL_E [3:0] $end
$var wire 4 Z ALU_SEL_D [3:0] $end
$var wire 32 [ ALUW [31:0] $end
$var wire 32 \ ALUMUX2_OUT [31:0] $end
$var wire 1 ] ALUMUX2_E $end
$var wire 1 ^ ALUMUX2_D $end
$var wire 32 _ ALUMUX1_OUT [31:0] $end
$var wire 1 ` ALUMUX1_E $end
$var wire 1 a ALUMUX1_D $end
$var wire 32 b ALUM [31:0] $end
$var wire 32 c ALUE [31:0] $end
$upscope $end
$upscope $end
$scope module NH_RegOp $end
$var reg 1 # clk $end
$var reg 1 $ reset $end
$var integer 32 d errors [31:0] $end
$var integer 32 e i [31:0] $end
$upscope $end
$enddefinitions $end
$comment Show the parameter values. $end
$dumpall
$end
#0
$dumpvars
bx e
bx d
bx c
bx b
xa
x`
bx _
x^
x]
bx \
bx [
bx Z
bx Y
xX
xW
bx V
bx U
bx T
bx S
bx R
bx Q
bx P
bx O
bx N
bx M
bx L
xK
xJ
xI
xH
bx G
bx F
bx E
bx D
bx C
bx B
bx A
bx @
bx ?
bx >
bx =
bx <
bx ;
bx :
bx 9
x8
x7
x6
x5
bx 4
bx 3
bx 2
bx 1
bx 0
bx /
bx .
bx -
bx ,
x+
x*
x)
bx (
x'
x&
x%
1$
0#
b100 "
x!
$end
#5000
b0 E
0+
0'
0K
0X
0I
b0 Z
0^
0a
b0 4
08
b0 .
b0 0
b100 ?
0!
b0 U
b0 L
b0 c
b0 V
b0 9
b0xxxxxxxx G
b0 >
b0 Q
b0 B
0W
b0 \
0]
b0 _
0`
b0 Y
0J
0H
b0 D
0*
0&
07
b0 3
b0 P
b0 =
b0 -
b0 /
b0 T
b0 A
b0 C
0)
0%
06
b0 2
b0 N
b0 ;
b0 ,
b0 b
b0 S
05
b0 (
b0 1
b0 M
b0 :
b0 F
b0 [
b0 R
b10001000100010001000000110111 O
b100 <
b0 @
1#
#6000
0$
#10000
0#
#15000
b11 4
18
bx .
bx 0
b10001000100010001000000000000 U
b1000010110111 O
b1000 ?
b1000 <
b0xxxxxxxx F
b100 >
b10001000100010001000000110111 Q
b100 @
1#
#20000
0#
#25000
b0 .
b0 0
b10000100110111 O
b1100 ?
b1100 <
b1000000000000 U
bx L
bx c
b10001000100010001000000000000 V
b10001000100010001000000000000 9
b1000 @
b1000 >
b1000010110111 Q
b100 B
17
b11 3
b10001000100010001000000110111 P
b100 =
bx \
bx -
bx /
b10001000100010001000000000000 T
1#
#30000
0#
#35000
b1000000000100 V
b1000000000100 9
b100 L
b100 c
b10000000000000 U
b11000110110111 O
b10000 ?
b10000 <
16
b11 2
b10001000100010001000000110111 N
b100 ;
bx ,
bx b
b10001000100010001000000000000 S
b1000010110111 P
b1000 =
b0 \
b0 -
b0 /
b1000000000000 T
b100 _
b100 A
b1100 >
b10000100110111 Q
b1000 B
b1100 @
1#
#40000
0#
#45000
b100001000110111 O
b10100 ?
b10100 <
b11000000000000 U
b10000000001000 V
b10000000001000 9
b1000 L
b1000 c
b10000 @
b10000 >
b11000110110111 Q
b1100 B
b10000100110111 P
b1100 =
b10000000000000 T
b1000 _
b1000 A
b1000010110111 N
b1000 ;
b0 ,
b100 b
b1000000000000 S
15
b11 1
b10001000100010001000000110111 M
b10001000100010001000000000000 (
b100 :
bx [
b10001000100010001000000000000 R
1#
#50000
0#
#55000
b11000000001100 V
b11000000001100 9
b1100 L
b1100 c
b100000000000000 U
b101001010110111 O
b11000 ?
b11000 <
b1000010110111 M
b1000 :
b100 [
b1000000000000 (
b1000000000000 R
b10000100110111 N
b1100 ;
b1000 b
b10000000000000 S
b11000110110111 P
b10000 =
b11000000000000 T
b1100 _
b1100 A
b10100 >
b100001000110111 Q
b10000 B
b10100 @
1#
#60000
0#
#65000
b110001100110111 O
b11100 ?
b11100 <
b101000000000000 U
b100000000010000 V
b100000000010000 9
b10000 L
b10000 c
b11000 @
b11000 >
b101001010110111 Q
b10100 B
b100001000110111 P
b10100 =
b100000000000000 T
b10000 _
b10000 A
b11000110110111 N
b10000 ;
b1100 b
b11000000000000 S
b10000100110111 M
b1100 :
b1000 [
b10000000000000 (
b10000000000000 R
1#
#70000
0#
#75000
b101000000010100 V
b101000000010100 9
b10100 L
b10100 c
b110000000000000 U
b111001110110111 O
b100000 ?
b100000 <
b11000110110111 M
b10000 :
b1100 [
b11000000000000 (
b11000000000000 R
b100001000110111 N
b10100 ;
b10000 b
b100000000000000 S
b101001010110111 P
b11000 =
b101000000000000 T
b10100 _
b10100 A
b11100 >
b110001100110111 Q
b11000 B
b11100 @
1#
#80000
0#
#85000
b1000010000110111 O
b100100 ?
b100100 <
b111000000000000 U
b110000000011000 V
b110000000011000 9
b11000 L
b11000 c
b100000 @
b100000 >
b111001110110111 Q
b11100 B
b110001100110111 P
b11100 =
b110000000000000 T
b11000 _
b11000 A
b101001010110111 N
b11000 ;
b10100 b
b101000000000000 S
b100001000110111 M
b10100 :
b10000 [
b100000000000000 (
b100000000000000 R
1#
#90000
0#
#95000
b1000000000000 0
b111000000011100 V
b111000000011100 9
b11100 L
b11100 c
b1000000000000000 U
b1001010010110111 O
b101000 ?
b101000 <
b101001010110111 M
b11000 :
b10100 [
b101000000000000 (
b101000000000000 R
b110001100110111 N
b11100 ;
b11000 b
b110000000000000 S
b111001110110111 P
b100000 =
b111000000000000 T
b11100 _
b11100 A
b100100 >
b1000010000110111 Q
b100000 B
b100100 @
1#
#100000
0#
#105000
b100001000000010010011 O
b101100 ?
b101100 <
b1001000000000000 U
b1000000000100000 V
b1000000000100000 9
b100000 L
b100000 c
b101000 @
b101000 >
b1001010010110111 Q
b100100 B
b1000010000110111 P
b100100 =
b1000000000000 /
b1000000000000000 T
b100000 _
b100000 A
b111001110110111 N
b100000 ;
b11100 b
b111000000000000 S
b110001100110111 M
b11100 :
b11000 [
b110000000000000 (
b110000000000000 R
1#
#110000
0#
#115000
1^
1a
b1 4
b1000000000000 .
b1001000000100100 V
b1001000000100100 9
b100100 L
b100100 c
b1 U
b10011 O
b110000 ?
b110000 <
b111001110110111 M
b100000 :
b11100 [
b111000000000000 (
b111000000000000 R
b1000010000110111 N
b100100 ;
b100000 b
b1000000000000000 S
b1001010010110111 P
b101000 =
b1001000000000000 T
b100100 _
b100100 A
b101100 >
b100001000000010010011 Q
b101000 B
b101100 @
1#
#120000
0#
#125000
b0 .
b0 0
b110100 ?
b110100 <
b0 U
b101001 V
b101001 9
b1000000000001 L
b1000000000001 c
b110000 @
b110000 >
b10011 Q
b101100 B
1]
1`
b1 3
b100001000000010010011 P
b101100 =
b1 \
b1000000000000 -
b1 T
b1000000000000 _
b101000 A
b1001010010110111 N
b101000 ;
b100100 b
b1001000000000000 S
b1000010000110111 M
b100100 :
b100000 [
b1000000000000000 (
b1000000000000000 R
1#
#130000
0#
#135000
b0 L
b0 c
b101100 V
b101100 9
b111000 ?
b111000 <
b1001010010110111 M
b101000 :
b100100 [
b1001000000000000 (
b1001000000000000 R
b1 2
b100001000000010010011 N
b101100 ;
b1000000000000 ,
b1000000000001 b
b1 S
b10011 P
b110000 =
b0 -
b0 _
b0 /
b0 \
b0 T
b101100 A
b110100 >
b110000 B
b110100 @
1#
#140000
0#
#145000
b111100 ?
b111100 <
b110000 V
b110000 9
b111000 @
b111000 >
b110100 B
b110100 =
b110000 A
b10011 N
b110000 ;
b0 ,
b0 b
b0 S
b1 1
b100001000000010010011 M
b101100 :
b1000000000001 [
b1000000000001 (
b1 R
1#
#150000
0#
#155000
b110100 V
b110100 9
b1000000 ?
b1000000 <
b10011 M
b110000 :
b0 (
b0 [
b0 R
b110100 ;
b111000 =
b110100 A
b111100 >
b111000 B
b111100 @
1#
#160000
0#
#165000
b1000100 ?
b1000100 <
b111000 V
b111000 9
b1000000 @
b1000000 >
b111100 B
b111100 =
b111000 A
b111000 ;
b110100 :
1#
#170000
0#
#175000
b111100 V
b111100 9
b1001000 ?
b1001000 <
b111000 :
b111100 ;
b1000000 =
b111100 A
b1000100 >
b1000000 B
b1000100 @
1#
#180000
0#
#185000
b100000000010100110011 O
b1001100 ?
b1001100 <
b1000000 V
b1000000 9
b1001000 @
b1001000 >
b1000100 B
b1000100 =
b1000000 A
b1000000 ;
b111100 :
1#
#190000
0#
#195000
0^
b1000000000001 .
b1000100 V
b1000100 9
b1000000000100000000010110110011 O
b1010000 ?
b1010000 <
b1000000 :
b1000100 ;
b1001000 =
b1000100 A
b1001100 >
b100000000010100110011 Q
b1001000 B
b1001100 @
1#
#200000
0#
#205000
b1 Z
b100000100011000110011 O
b1010100 ?
b1010100 <
b1000000000001 L
b1000000000001 c
b1001000 V
b1001000 9
b1010000 @
b1010000 >
b1000000000100000000010110110011 Q
b1001100 B
b1000000000001 \
0]
b100000000010100110011 P
b1001100 =
b1000000000001 -
b1001000 A
b1001000 ;
b1000100 :
1#
#210000
0#
#215000
b10 Z
b11111111111111111110111111111111 L
b11111111111111111110111111111111 c
b1001100 V
b1001100 9
b100100001110011100110011 O
b1011000 ?
b1011000 <
b1001000 :
b100000000010100110011 N
b1001100 ;
b1000000000001 ,
b1000000000001 b
b1 Y
b1000000000100000000010110110011 P
b1010000 =
b1001100 A
b1010100 >
b100000100011000110011 Q
b1010000 B
b1010100 @
1#
#220000
0#
#225000
b11 Z
b1001000000000000 .
b1000000000001 0
b100100001111011110110011 O
b1011100 ?
b1011100 <
b1000000000001 L
b1000000000001 c
b1010000 V
b1010000 9
b1011000 @
b1011000 >
b100100001110011100110011 Q
b1010100 B
b10 Y
b100000100011000110011 P
b1010100 =
b1010000 A
b1000000000100000000010110110011 N
b1010000 ;
b11111111111111111110111111111111 b
b100000000010100110011 M
b1001100 :
b1000000000001 (
b1000000000001 [
1#
#230000
0#
#235000
b100 Z
b1001000000000001 L
b1001000000000001 c
b1010100 V
b1010100 9
b100010001100000110011 O
b1100000 ?
b1100000 <
b1000000000100000000010110110011 M
b1010000 :
b11111111111111111110111111111111 (
b11111111111111111110111111111111 [
b100000100011000110011 N
b1010100 ;
b1000000000001 b
b11 Y
b100100001110011100110011 P
b1011000 =
b1001000000000000 \
b1001000000000000 -
b1000000000001 _
b1000000000001 /
b1010100 A
b1011100 >
b100100001111011110110011 Q
b1011000 B
b1011100 @
1#
#240000
0#
#245000
b101 Z
b1000000000001 .
b10000000000000 0
b100010101100010110011 O
b1100100 ?
b1100100 <
b1000000000000 L
b1000000000000 c
b1011000 V
b1011000 9
b1100000 @
b1100000 >
b100010001100000110011 Q
b1011100 B
b100 Y
b100100001111011110110011 P
b1011100 =
b1011000 A
b100100001110011100110011 N
b1011000 ;
b1001000000000000 ,
b1001000000000001 b
b100000100011000110011 M
b1010100 :
b1000000000001 (
b1000000000001 [
1#
#250000
0#
#255000
b110 Z
b100000000000000 L
b100000000000000 c
b1011100 V
b1011100 9
b1000000000100010101100100110011 O
b1101000 ?
b1101000 <
b100100001110011100110011 M
b1011000 :
b1001000000000001 (
b1001000000000001 [
b100100001111011110110011 N
b1011100 ;
b1000000000000 b
b101 Y
b100010001100000110011 P
b1100000 =
b1000000000001 \
b1000000000001 -
b10000000000000 _
b10000000000000 /
b1011100 A
b1100100 >
b100010101100010110011 Q
b1100000 B
b1100100 @
1#
#260000
0#
#265000
b111 Z
b1000001010100110110011 O
b1101100 ?
b1101100 <
b1000000000000 L
b1000000000000 c
b1100000 V
b1100000 9
b1101000 @
b1101000 >
b1000000000100010101100100110011 Q
b1100100 B
b110 Y
b100010101100010110011 P
b1100100 =
b1100000 A
b100010001100000110011 N
b1100000 ;
b1000000000001 ,
b100000000000000 b
b100100001111011110110011 M
b1011100 :
b1000000000000 (
b1000000000000 [
1#
#270000
0#
#275000
b1000 Z
b10000000000000 .
b1000000000001 0
b1100100 V
b1100100 9
b1000001011101000110011 O
b1110000 ?
b1110000 <
b100010001100000110011 M
b1100000 :
b100000000000000 (
b100000000000000 [
b100010101100010110011 N
b1100100 ;
b1000000000000 b
b111 Y
b1000000000100010101100100110011 P
b1101000 =
b1100100 A
b1101100 >
b1000001010100110110011 Q
b1101000 B
b1101100 @
1#
#280000
0#
#285000
b1001 Z
bx O
b1110100 ?
b1110100 <
b1 L
b1 c
b1101000 V
b1101000 9
b1110000 @
b1110000 >
b1000001011101000110011 Q
b1101100 B
b1000 Y
b1000001010100110110011 P
b1101100 =
b10000000000000 \
b10000000000000 -
b1000000000001 _
b1000000000001 /
b1101000 A
b1000000000100010101100100110011 N
b1101000 ;
b100010101100010110011 M
b1100100 :
b1000000000000 (
b1000000000000 [
1#
#290000
0#
#295000
b0 Z
0a
b0 4
08
bx .
bx 0
b1101100 V
b1101100 9
b1111000 ?
b1111000 <
b1000000000100010101100100110011 M
b1101000 :
b1000001010100110110011 N
b1101100 ;
b10000000000000 ,
b1 b
b1001 Y
b1000001011101000110011 P
b1110000 =
b1101100 A
b1110100 >
bx Q
b1110000 B
b1110100 @
1#
#300000
0#
#305000
b1111100 ?
b1111100 <
bx L
bx c
b1110000 V
b1110000 9
b1111000 @
b1111000 >
b1110100 B
0`
b0 Y
07
b0 3
bx P
b1110100 =
bx \
bx -
b1110000 _
bx /
b1110000 A
b1000001011101000110011 N
b1110000 ;
b1000001010100110110011 M
b1101100 :
b1 (
b1 [
1#
#310000
0#
#315000
b1110100 V
b1110100 9
b10000000 ?
b10000000 <
b1000001011101000110011 M
b1110000 :
06
b0 2
bx N
b1110100 ;
bx ,
bx b
b1111000 =
b1110100 _
b1110100 A
b1111100 >
b1111000 B
b1111100 @
1#
#320000
0#
#325000
b10000100 ?
b10000100 <
b1111000 V
b1111000 9
b10000000 @
b10000000 >
b1111100 B
b1111100 =
b1111000 _
b1111000 A
b1111000 ;
05
b0 1
bx M
b1110100 :
b1110100 (
bx [
1#
#330000
0#
#335000
b1111100 V
b1111100 9
b10001000 ?
b10001000 <
b1111000 (
b1111000 :
b1111100 ;
b10000000 =
b1111100 _
b1111100 A
b10000100 >
b10000000 B
b10000100 @
1#
#340000
0#
#345000
b10001100 ?
b10001100 <
b10000000 V
b10000000 9
b10001000 @
b10001000 >
b10000100 B
b10000100 =
b10000000 _
b10000000 A
b10000000 ;
b1111100 (
b1111100 :
1#
#350000
0#
#355000
b10000100 V
b10000100 9
b10010000 ?
b10010000 <
b10000000 (
b10000000 :
b10000100 ;
b10001000 =
b10000100 _
b10000100 A
b10001100 >
b10001000 B
b10001100 @
1#
#360000
0#
#365000
b10010100 ?
b10010100 <
b10001000 V
b10001000 9
b10010000 @
b10010000 >
b10001100 B
b10001100 =
b10001000 _
b10001000 A
b10001000 ;
b10000100 (
b10000100 :
1#
#370000
0#
#375000
b10001100 V
b10001100 9
b10011000 ?
b10011000 <
b10001000 (
b10001000 :
b10001100 ;
b10010000 =
b10001100 _
b10001100 A
b10010100 >
b10010000 B
b10010100 @
1#
#380000
0#
#385000
b10011100 ?
b10011100 <
b10010000 V
b10010000 9
b10011000 @
b10011000 >
b10010100 B
b10010100 =
b10010000 _
b10010000 A
b10010000 ;
b10001100 (
b10001100 :
1#
#390000
0#
#395000
b10010100 V
b10010100 9
b10100000 ?
b10100000 <
b10010000 (
b10010000 :
b10010100 ;
b10011000 =
b10010100 _
b10010100 A
b10011100 >
b10011000 B
b10011100 @
1#
#400000
0#
#405000
b10100100 ?
b10100100 <
b10011000 V
b10011000 9
b10100000 @
b10100000 >
b10011100 B
b10011100 =
b10011000 _
b10011000 A
b10011000 ;
b10010100 (
b10010100 :
1#
#410000
0#
#415000
b10011100 V
b10011100 9
b10101000 ?
b10101000 <
b10011000 (
b10011000 :
b10011100 ;
b10100000 =
b10011100 _
b10011100 A
b10100100 >
b10100000 B
b10100100 @
1#
#420000
0#
#425000
b10101100 ?
b10101100 <
b10100000 V
b10100000 9
b10101000 @
b10101000 >
b10100100 B
b10100100 =
b10100000 _
b10100000 A
b10100000 ;
b10011100 (
b10011100 :
1#
#430000
0#
#435000
b10100100 V
b10100100 9
b10110000 ?
b10110000 <
b10100000 (
b10100000 :
b10100100 ;
b10101000 =
b10100100 _
b10100100 A
b10101100 >
b10101000 B
b10101100 @
1#
#440000
0#
#445000
b10110100 ?
b10110100 <
b10101000 V
b10101000 9
b10110000 @
b10110000 >
b10101100 B
b10101100 =
b10101000 _
b10101000 A
b10101000 ;
b10100100 (
b10100100 :
1#
#450000
0#
#455000
b10101100 V
b10101100 9
b10111000 ?
b10111000 <
b10101000 (
b10101000 :
b10101100 ;
b10110000 =
b10101100 _
b10101100 A
b10110100 >
b10110000 B
b10110100 @
1#
#460000
0#
#465000
b10111100 ?
b10111100 <
b10110000 V
b10110000 9
b10111000 @
b10111000 >
b10110100 B
b10110100 =
b10110000 _
b10110000 A
b10110000 ;
b10101100 (
b10101100 :
1#
#470000
0#
#475000
b10110100 V
b10110100 9
b11000000 ?
b11000000 <
b10110000 (
b10110000 :
b10110100 ;
b10111000 =
b10110100 _
b10110100 A
b10111100 >
b10111000 B
b10111100 @
1#
#480000
0#
#485000
b11000100 ?
b11000100 <
b10111000 V
b10111000 9
b11000000 @
b11000000 >
b10111100 B
b10111100 =
b10111000 _
b10111000 A
b10111000 ;
b10110100 (
b10110100 :
1#
#490000
0#
#495000
b10111100 V
b10111100 9
b11001000 ?
b11001000 <
b10111000 (
b10111000 :
b10111100 ;
b11000000 =
b10111100 _
b10111100 A
b11000100 >
b11000000 B
b11000100 @
1#
#500000
0#
#505000
b11001100 ?
b11001100 <
b11000000 V
b11000000 9
b11001000 @
b11001000 >
b11000100 B
b11000100 =
b11000000 _
b11000000 A
b11000000 ;
b10111100 (
b10111100 :
b10101 e
b0 d
1#
