src/RegisterFile.v

module register_file(
    input clk, 
    input we,
    input [4:0] raddr1, //address to read from
    input [4:0] raddr2, //32 registers so 5 bits
    input [4:0] waddr, //address to write to
    input [31:0] wdata, //data to write
    output [31:0] rdata1, //data read
    output [31:0] rdata2
);

    //32 registers
    //not really gonna use the first one, but complicates to remove it
    reg [31:0] register [31:0];

    //read
    //async for single cycle reasons
    //turnary operator is used since we don't know the initial state of register[0]
    assign rdata1 = (raddr1 == 5'd0) ? 32'd0 : register[raddr1];
    assign rdata2 = (raddr2 == 5'd0) ? 32'd0 : register[raddr2];

    //write
    always @(posedge clk) begin
        if(we && (waddr != 5'd0))
            register[waddr] <= wdata;
    end

endmodule

tb/tb_RegisterFile.v
`timescale 1ns/1ps

module tb_RegisterFile;

    reg clk;
    reg we;
    
    reg [4:0] raddr1;
    reg [4:0] raddr2;
    reg [4:0] waddr;

    reg [31:0] wdata;

    wire [31:0] rdata1;
    wire [31:0] rdata2;

    register_file test_register_file (
        .clk(clk),
        .we(we),
        .raddr1(raddr1),
        .raddr2(raddr2),
        .waddr(waddr),
        .wdata(wdata),
        .rdata1(rdata1),
        .rdata2(rdata2)
    );    

    always #20 clk = ~clk;

    initial begin
        clk = 1'b0;

        $dumpfile("sim/register_file.vcd");
        $dumpvars(0, tb_RegisterFile);
        
        //simple write then read test (WR = Write then Read)
        we = 1'b1; waddr = 5'd5; wdata = 32'd42; 

        @(posedge clk) 
        #2;
        we = 1'b0; raddr1 = 5'd5; raddr2 = 5'd5;
        #10
        if (rdata1 != 32'd42)
            $display("FAIL WR DATA1: expected 42, got %0d", rdata1);
        else if(rdata2 != 32'd42)
            $display("FAIL WR DATA2: expected 42, got %0d", rdata2);
        else
            $display("PASS WR");

        //write to register[0]
        we = 1'b1; waddr = 5'd0; wdata = 32'd42; 

        @(posedge clk)
        #2;
        we = 1'b0; raddr1 = 5'd0; raddr2 = 5'd0;
        #10
        if (rdata1 != 32'd0)
            $display("FAIL W to 0: expected 0, got %0d", rdata1);
        else if(rdata2 != 32'd0)
            $display("FAIL W to 0: expected 0, got %0d", rdata2);
        else
            $display("PASS W to 0");

        //write but incorrect we
        we = 1'b0; waddr = 5'd10; wdata = 32'd35; 

        @(posedge clk)
        #2;
        we = 1'b0; raddr1 = 5'd10; raddr2 = 5'd10;
        #10
        if (rdata1 != 32'd0)
            $display("FAIL W we0: expected 0, got %0d", rdata1);
        else if(rdata2 != 32'd0)
            $display("FAIL W we0: expected 0, got %0d", rdata2);
        else
            $display("PASS W we0");

        //Reading from two different places at once
        we = 1'b1; waddr = 5'd10; wdata = 32'd35; 

        @(posedge clk) 
        #2;
        we = 1'b0; raddr1 = 5'd5; raddr2 = 5'd10;
        #10
        if (rdata1 != 32'd42)
            $display("FAIL double R: expected 42, got %0d", rdata1);
        else if(rdata2 != 32'd35)
            $display("FAIL double R: expected 35, got %0d", rdata2);
        else
            $display("PASS double R");

        
        $finish;
    end

endmodule

sim/register_file.vcd
$date
	Mon May 25 08:22:45 2026
$end
$version
	Icarus Verilog
$end
$timescale
	1ps
$end
$scope module tb_RegisterFile $end
$var wire 32 ! rdata2 [31:0] $end
$var wire 32 " rdata1 [31:0] $end
$var reg 1 # clk $end
$var reg 5 $ raddr1 [4:0] $end
$var reg 5 % raddr2 [4:0] $end
$var reg 5 & waddr [4:0] $end
$var reg 32 ' wdata [31:0] $end
$var reg 1 ( we $end
$scope module test_register_file $end
$var wire 1 # clk $end
$var wire 5 ) raddr1 [4:0] $end
$var wire 5 * raddr2 [4:0] $end
$var wire 5 + waddr [4:0] $end
$var wire 32 , wdata [31:0] $end
$var wire 1 ( we $end
$var wire 32 - rdata2 [31:0] $end
$var wire 32 . rdata1 [31:0] $end
$upscope $end
$upscope $end
$enddefinitions $end
$comment Show the parameter values. $end
$dumpall
$end
#0
$dumpvars
bx .
bx -
b101010 ,
b101 +
bx *
bx )
1(
b101010 '
b101 &
bx %
bx $
0#
bx "
bx !
$end
#20000
1#
#22000
b101010 !
b101010 -
b101010 "
b101010 .
b101 %
b101 *
b101 $
b101 )
0(
#32000
b0 &
b0 +
1(
#40000
0#
#60000
1#
#62000
b0 !
b0 -
b0 "
b0 .
b0 %
b0 *
b0 $
b0 )
0(
#72000
b100011 '
b100011 ,
b1010 &
b1010 +
#80000
0#
#100000
1#
#102000
bx !
bx -
bx "
bx .
b1010 %
b1010 *
b1010 $
b1010 )
#112000
1(
#120000
0#
#140000
b100011 "
b100011 .
b100011 !
b100011 -
1#
#142000
b101010 "
b101010 .
b101 $
b101 )
0(
