src/ImmediateGenerator.v
module immediate_generator (
    input [31:0] data_in,
    output reg [31:0] data_out
);

always @(*) begin
    data_out = 32'd0;
    case(data_in[6:0])
        //I-type
        7'b0010011, 7'b0000011, 7'b1100111: begin
            data_out = {{21{data_in[31]}}, data_in[30:20]};
        end
        //S-Type
        7'b0100011: begin
            data_out = {{21{data_in[31]}}, data_in[30:25], data_in[11:7]};
        end
        //B-Type
        7'b1100011: begin
            data_out = {{20{data_in[31]}}, data_in[7], data_in[30:25], data_in[11:8], 1'b0};
        end
        //U-Type
        7'b0110111, 7'b0010111: begin
            data_out = {data_in[31:12], 12'd0};
        end
        //J-Type
        7'b1101111: begin
            data_out = {{12{data_in[31]}}, data_in[19:12], data_in[20], data_in[30:21], 1'b0};
        end

        default: data_out = 32'd0;
    endcase
end


endmodule

tb/tb_ImmediateGenerator.v
`timescale 1ns/1ps

module tb_ImmediateGenerator;

    reg [31:0] data_in;

    reg [6:0] opcode;

    reg [11:0] immi, imms;
    reg [12:0] immb;
    reg [19:0] immu;
    reg [20:0] immj;

    wire [31:0] data_out;

    immediate_generator test_immediate_generator_t (
        .data_in(data_in),
        .data_out(data_out)
    );


    initial begin
        $dumpfile("sim/tb_immediate_generator.vcd");
        $dumpvars(0, tb_ImmediateGenerator);

        // I-type
        opcode = 7'b0010011;
        immi = 12'd15;
        data_in = {immi, {13{1'b0}}, opcode};

        #10;
        if(data_out != 32'd15)
            $display("FAIL ITYPE POS 1: expected 15, got %0d", data_out);
        else
            $display("PASS ITYPE POS 1");

        immi = -12'd10;
        data_in = {immi, {13{1'b0}}, opcode};

        #10;
        if(data_out != -32'd10)
            $display("FAIL ITYPE NEG 1: expected -10, got %0d", data_out);
        else
            $display("PASS ITYPE NEG 1");

        opcode = 7'b0000011;
        immi = 12'd14;
        data_in = {immi, {13{1'b0}}, opcode};

        #10;
        if(data_out != 32'd14)
            $display("FAIL ITYPE POS 2: expected 14, got %0d", data_out);
        else
            $display("PASS ITYPE POS 2");
            
        immi = -12'd9;
        data_in = {immi, {13{1'b0}}, opcode};

        #10;
        if(data_out != -32'd9)
            $display("FAIL ITYPE NEG 2: expected -9, got %0d", data_out);
        else
            $display("PASS ITYPE NEG 2");

        opcode = 7'b1100111;
        immi = 12'd13;
        data_in = {immi, {13{1'b0}}, opcode};

        #10;
        if(data_out != 32'd13)
            $display("FAIL ITYPE POS 3: expected 13, got %0d", data_out);
        else
            $display("PASS ITYPE POS 3");
            
        immi = -12'd8;
        data_in = {immi, {13{1'b0}}, opcode};

        #10;
        if(data_out != -32'd8)
            $display("FAIL ITYPE NEG 3: expected -8, got %0d", data_out);
        else
            $display("PASS ITYPE NEG 3");
        
        // S-type
        opcode = 7'b0100011;
        imms = 12'd21;
        data_in = {imms[11:5], {13{1'b0}}, imms[4:0], opcode};

        #10;
        if(data_out != 32'd21)
            $display("FAIL STYPE POS: expected 21, got %0d", data_out);
        else
            $display("PASS STYPE POS");

        imms = -12'd3;
        data_in = {imms[11:5], {13{1'b0}}, imms[4:0], opcode};

        #10;
        if(data_out != -32'd3)
            $display("FAIL STYPE NEG: expected -3, got %0d", data_out);
        else
            $display("PASS STYPE NEG");

        // B-type
        opcode = 7'b1100011;
        immb = 13'd100;
        data_in = {immb[12], immb[10:5], {13{1'b0}}, immb[4:1], immb[11], opcode};

        #10;
        if(data_out != 32'd100)
            $display("FAIL BTYPE POS: expected 100, got %0d", data_out);
        else
            $display("PASS BTYPE POS");

        immb = -13'd15;
        data_in = {immb[12], immb[10:5], {13{1'b0}}, immb[4:1], immb[11], opcode};

        #10;
        if(data_out != -32'd16)
            $display("FAIL BTYPE NEG: expected -16, got %0d", data_out);
        else
            $display("PASS BTYPE NEG");

        // U-type
        opcode = 7'b0110111;
        immu = 20'd53;
        data_in = {immu, {5{1'b0}}, opcode};

        #10;
        if(data_out != {20'd53, 12'd0})
            $display("FAIL UTYPE POS1: expected %0d, got %0d", {20'd53, 12'd0}, data_out);
        else
            $display("PASS UTYPE POS1");

        immu = -20'd43;
        data_in = {immu, {5{1'b0}}, opcode};

        #10;
        if(data_out != {-20'd43, 12'd0})
            $display("FAIL UTYPE NEG1: expected %0d, got %0d", {-20'd43, 12'd0}, data_out);
        else
            $display("PASS UTYPE NEG1");

        opcode = 7'b0010111;
        immu = 20'd52;
        data_in = {immu, {5{1'b0}}, opcode};

        #10;
        if(data_out != {20'd52, 12'd0})
            $display("FAIL UTYPE POS2: expected %0d, got %0d", {20'd52, 12'd0}, data_out);
        else
            $display("PASS UTYPE POS2");

        immu = -20'd42;
        data_in = {immu, {5{1'b0}}, opcode};

        #10;
        if(data_out != {-20'd42, 12'd0})
            $display("FAIL UTYPE NEG2: expected %0d, got %0d", {-20'd42, 12'd0}, data_out);
        else
            $display("PASS UTYPE NEG2");

        // J-type
        opcode = 7'b1101111;
        immj = 21'd33;
        data_in = {immj[20], immj[10:1], immj[11], immj[19:12], {5{1'b0}}, opcode};

        #10;
        if(data_out != 32'd32)
            $display("FAIL JTYPE POS: expected 32, got %0d", data_out);
        else
            $display("PASS JTYPE POS");

        immj = -21'd34;
        data_in = {immj[20], immj[10:1], immj[11], immj[19:12], {5{1'b0}}, opcode};

        #10;
        if(data_out != -32'd34)
            $display("FAIL JTYPE NEG: expected -34, got %0d", data_out);
        else
            $display("PASS JTYPE NEG");

        // Default
        opcode = 7'b0000000;
        data_in = {25'b1111111111111111111111111, opcode};

        #10;
        if(data_out != 32'd0)
            $display("FAIL DEFAULT: expected 0, got %0d", data_out);
        else
            $display("PASS DEFAULT");

        $finish;
    end

endmodule

sim/tb_immediate_generator.vcd
$date
	Wed Jun  3 04:30:12 2026
$end
$version
	Icarus Verilog
$end
$timescale
	1ps
$end
$scope module tb_ImmediateGenerator $end
$var wire 32 ! data_out [31:0] $end
$var reg 32 " data_in [31:0] $end
$var reg 13 # immb [12:0] $end
$var reg 12 $ immi [11:0] $end
$var reg 21 % immj [20:0] $end
$var reg 12 & imms [11:0] $end
$var reg 20 ' immu [19:0] $end
$var reg 7 ( opcode [6:0] $end
$scope module test_immediate_generator_t $end
$var wire 32 ) data_in [31:0] $end
$var reg 32 * data_out [31:0] $end
$upscope $end
$upscope $end
$enddefinitions $end
$comment Show the parameter values. $end
$dumpall
$end
#0
$dumpvars
b1111 *
b111100000000000000010011 )
b10011 (
bx '
bx &
bx %
b1111 $
bx #
b111100000000000000010011 "
b1111 !
$end
#10000
b11111111111111111111111111110110 !
b11111111111111111111111111110110 *
b11111111011000000000000000010011 "
b11111111011000000000000000010011 )
b111111110110 $
#20000
b1110 !
b1110 *
b111000000000000000000011 "
b111000000000000000000011 )
b1110 $
b11 (
#30000
b11111111111111111111111111110111 !
b11111111111111111111111111110111 *
b11111111011100000000000000000011 "
b11111111011100000000000000000011 )
b111111110111 $
#40000
b1101 !
b1101 *
b110100000000000001100111 "
b110100000000000001100111 )
b1101 $
b1100111 (
#50000
b11111111111111111111111111111000 !
b11111111111111111111111111111000 *
b11111111100000000000000001100111 "
b11111111100000000000000001100111 )
b111111111000 $
#60000
b10101 !
b10101 *
b101010100011 "
b101010100011 )
b10101 &
b100011 (
#70000
b11111111111111111111111111111101 !
b11111111111111111111111111111101 *
b11111110000000000000111010100011 "
b11111110000000000000111010100011 )
b111111111101 &
#80000
b1100100 !
b1100100 *
b110000000000000001001100011 "
b110000000000000001001100011 )
b1100100 #
b1100011 (
#90000
b11111111111111111111111111110000 !
b11111111111111111111111111110000 *
b11111110000000000000100011100011 "
b11111110000000000000100011100011 )
b1111111110001 #
#100000
b110101000000000000 !
b110101000000000000 *
b110101000000110111 "
b110101000000110111 )
b110101 '
b110111 (
#110000
b11111111111111010101000000000000 !
b11111111111111010101000000000000 *
b11111111111111010101000000110111 "
b11111111111111010101000000110111 )
b11111111111111010101 '
#120000
b110100000000000000 !
b110100000000000000 *
b110100000000010111 "
b110100000000010111 )
b110100 '
b10111 (
#130000
b11111111111111010110000000000000 !
b11111111111111010110000000000000 *
b11111111111111010110000000010111 "
b11111111111111010110000000010111 )
b11111111111111010110 '
#140000
b100000 !
b100000 *
b10000000000000000001101111 "
b10000000000000000001101111 )
b100001 %
b1101111 (
#150000
b11111111111111111111111111011110 !
b11111111111111111111111111011110 *
b11111101111111111111000001101111 "
b11111101111111111111000001101111 )
b111111111111111011110 %
#160000
b0 !
b0 *
b11111111111111111111111110000000 "
b11111111111111111111111110000000 )
b0 (
